{"2016120402":{"away":{"abbr":"SF","score":{"4":0,"T":6,"1":0,"3":0,"2":6,"5":0},"stats":{"passing":{"00-0027948":{"yds":35,"ints":0,"att":10,"twoptm":0,"cmp":4,"name":"B.Gabbert","twopta":0,"tds":0},"00-0027974":{"yds":4,"ints":0,"att":5,"twoptm":0,"cmp":1,"name":"C.Kaepernick","twopta":0,"tds":0}},"fumbles":{"00-0027974":{"yds":0,"lost":0,"trcv":0,"rcv":0,"tot":1,"name":"C.Kaepernick"},"00-0033151":{"yds":0,"lost":0,"trcv":1,"rcv":1,"tot":0,"name":"J.Garnett"},"00-0031298":{"yds":0,"lost":0,"trcv":1,"rcv":0,"tot":0,"name":"J.Ward"}},"puntret":{"00-0031061":{"lngtd":0,"lng":25,"ret":1,"avg":25,"name":"D.Johnson","tds":0}},"team":{"penyds":106,"pyds":6,"pen":11,"pt":8,"ryds":141,"totfd":10,"trnovr":0,"ptavg":38,"ptyds":308,"top":"28:42","totyds":147},"kicking":{"00-0004091":{"xpmade":0,"xpa":0,"xpb":0,"fga":2,"fgm":2,"xpmissed":0,"name":"P.Dawson","xptot":0,"fgyds":31,"totpfg":6}},"receiving":{"00-0031854":{"yds":6,"lngtd":0,"lng":6,"twoptm":0,"twopta":0,"name":"C.Harper","rec":1,"tds":0},"00-0030470":{"yds":9,"lngtd":0,"lng":5,"twoptm":0,"twopta":0,"name":"V.McDonald","rec":2,"tds":0},"00-0028091":{"yds":18,"lngtd":0,"lng":18,"twoptm":0,"twopta":0,"name":"J.Kerley","rec":1,"tds":0},"00-0031045":{"yds":6,"lngtd":0,"lng":6,"twoptm":0,"twopta":0,"name":"C.Hyde","rec":1,"tds":0}},"defense":{"00-0030088":{"tkl":1,"int":0,"name":"Q.Dial","sk":0,"ffum":0,"ast":0},"00-0030385":{"tkl":5,"int":0,"name":"G.Hodges","sk":0,"ffum":0,"ast":0},"00-0024421":{"tkl":4,"int":0,"name":"A.Bethea","sk":0,"ffum":0,"ast":1},"00-0031298":{"tkl":3,"int":0,"name":"J.Ward","sk":0,"ffum":0,"ast":0},"00-0024495":{"tkl":2,"int":0,"name":"A.Brooks","sk":1,"ffum":0,"ast":0},"00-0030106":{"tkl":1,"int":0,"name":"C.Jones","sk":0,"ffum":0,"ast":1},"00-0028292":{"tkl":9,"int":0,"name":"N.Bellore","sk":0,"ffum":0,"ast":2},"00-0032410":{"tkl":1,"int":0,"name":"R.Robinson","sk":0,"ffum":0,"ast":0},"00-0032057":{"tkl":3,"int":0,"name":"J.Tartt","sk":0,"ffum":0,"ast":1},"00-0027375":{"tkl":3,"int":0,"name":"T.Brock","sk":0,"ffum":0,"ast":0},"00-0032060":{"tkl":1,"int":0,"name":"E.Harold","sk":0,"ffum":0,"ast":0},"00-0032378":{"tkl":4,"int":0,"name":"D.Buckner","sk":0,"ffum":0,"ast":1},"00-0028836":{"tkl":2,"int":0,"name":"M.Wilhoite","sk":0,"ffum":0,"ast":0},"00-0026145":{"tkl":4,"int":0,"name":"G.Dorsey","sk":0,"ffum":0,"ast":2}},"kickret":{"00-0032137":{"lngtd":0,"lng":24,"ret":3,"avg":19,"name":"J.Shepherd","tds":0}},"rushing":{"00-0028202":{"yds":20,"att":5,"lngtd":0,"lng":9,"twoptm":0,"twopta":0,"name":"S.Draughn","tds":0},"00-0027948":{"yds":1,"att":1,"lngtd":0,"lng":1,"twoptm":0,"twopta":0,"name":"B.Gabbert","tds":0},"00-0027974":{"yds":20,"att":6,"lngtd":0,"lng":14,"twoptm":0,"twopta":0,"name":"C.Kaepernick","tds":0},"00-0028409":{"yds":8,"att":2,"lngtd":0,"lng":9,"twoptm":0,"twopta":0,"name":"D.Harris","tds":0},"00-0031045":{"yds":92,"att":20,"lngtd":0,"lng":12,"twoptm":0,"twopta":0,"name":"C.Hyde","tds":0}},"punting":{"00-0032065":{"yds":308,"lng":44,"pts":8,"avg":38,"name":"B.Pinion","i20":2}}},"players":null,"to":2},"clock":"00:39","down":0,"drives":{"19":{"qtr":4,"fds":1,"plays":{"3318":{"sp":0,"desc":"Timeout at 12:11.","qtr":4,"down":0,"players":{},"ydsnet":18,"posteam":"","time":"12:11","ydstogo":0,"yrdln":"","note":"Timeout"},"3243":{"sp":0,"desc":"C.Barth kicks 65 yards from CHI 35 to SF 0. J.Shepherd to SF 16 for 16 yards (S.McManis).","qtr":4,"down":0,"players":{"00-0027743":[{"statId":79,"yards":0,"clubcode":"CHI","sequence":4,"playerName":"S.McManis"}],"00-0032137":[{"statId":45,"yards":16,"clubcode":"SF","sequence":2,"playerName":"J.Shepherd"}],"00-0026138":[{"statId":43,"yards":65,"clubcode":"CHI","sequence":1,"playerName":"C.Barth"},{"statId":42,"yards":0,"clubcode":"CHI","sequence":3,"playerName":"C.Barth"}]},"ydsnet":0,"posteam":"CHI","time":"12:55","ydstogo":0,"yrdln":"CHI 35","note":"KICKOFF"},"3335":{"sp":0,"desc":"(12:11) (Shotgun) B.Gabbert pass incomplete short left to T.Smith.","qtr":4,"down":2,"players":{"00-0027996":[{"statId":115,"yards":0,"clubcode":"SF","sequence":2,"playerName":"T.Smith"}],"00-0027948":[{"statId":14,"yards":0,"clubcode":"SF","sequence":1,"playerName":"B.Gabbert"},{"statId":112,"yards":5,"clubcode":"SF","sequence":3,"playerName":"B.Gabbert"}]},"ydsnet":18,"posteam":"SF","time":"12:11","ydstogo":10,"yrdln":"SF 34","note":null},"3379":{"sp":0,"desc":"(12:03) (Punt formation) B.Pinion punts 38 yards to CHI 28, Center-K.Nelson. B.Callahan to CHI 31 for 3 yards (K.Nelson).","qtr":4,"down":4,"players":{"00-0028374":[{"statId":79,"yards":0,"clubcode":"SF","sequence":3,"playerName":"K.Nelson"}],"00-0032065":[{"statId":29,"yards":38,"clubcode":"SF","sequence":1,"playerName":"B.Pinion"}],"00-0031904":[{"statId":33,"yards":3,"clubcode":"CHI","sequence":2,"playerName":"B.Callahan"}]},"ydsnet":18,"posteam":"SF","time":"12:03","ydstogo":10,"yrdln":"SF 34","note":"PUNT"},"3265":{"sp":0,"desc":"(12:51) Gabbert, Blaine in at QB for SF (Shotgun) B.Gabbert pass deep right to J.Kerley to SF 34 for 18 yards (N.Kwiatkoski).","qtr":4,"down":1,"players":{"00-0027948":[{"statId":15,"yards":18,"clubcode":"SF","sequence":2,"playerName":"B.Gabbert"},{"statId":111,"yards":18,"clubcode":"SF","sequence":3,"playerName":"B.Gabbert"}],"0":[{"statId":4,"yards":0,"clubcode":"SF","sequence":1,"playerName":""}],"00-0028091":[{"statId":21,"yards":18,"clubcode":"SF","sequence":4,"playerName":"J.Kerley"},{"statId":115,"yards":0,"clubcode":"SF","sequence":5,"playerName":"J.Kerley"},{"statId":113,"yards":0,"clubcode":"SF","sequence":6,"playerName":"J.Kerley"}],"00-0032773":[{"statId":79,"yards":0,"clubcode":"CHI","sequence":7,"playerName":"N.Kwiatkoski"}]},"ydsnet":18,"posteam":"SF","time":"12:51","ydstogo":10,"yrdln":"SF 16","note":null},"3357":{"sp":0,"desc":"(12:07) (No Huddle, Shotgun) B.Gabbert pass incomplete short right to V.McDonald.","qtr":4,"down":3,"players":{"00-0030470":[{"statId":115,"yards":0,"clubcode":"SF","sequence":3,"playerName":"V.McDonald"}],"00-0027948":[{"statId":14,"yards":0,"clubcode":"SF","sequence":2,"playerName":"B.Gabbert"},{"statId":112,"yards":4,"clubcode":"SF","sequence":4,"playerName":"B.Gabbert"}],"0":[{"statId":7,"yards":0,"clubcode":"SF","sequence":1,"playerName":""}]},"ydsnet":18,"posteam":"SF","time":"12:07","ydstogo":10,"yrdln":"SF 34","note":null},"3293":{"sp":0,"desc":"(12:17) (No Huddle, Shotgun) B.Gabbert pass incomplete deep left to C.Hyde. CHI-C.LeBlanc was injured during the play.","qtr":4,"down":1,"players":{"00-0027948":[{"statId":14,"yards":0,"clubcode":"SF","sequence":1,"playerName":"B.Gabbert"},{"statId":112,"yards":16,"clubcode":"SF","sequence":3,"playerName":"B.Gabbert"}],"00-0031045":[{"statId":115,"yards":0,"clubcode":"SF","sequence":2,"playerName":"C.Hyde"}]},"ydsnet":18,"posteam":"SF","time":"12:17","ydstogo":10,"yrdln":"SF 34","note":null}},"redzone":true,"end":{"qtr":4,"time":"11:54","yrdln":"SF 34","team":"SF"},"start":{"qtr":4,"time":"12:55","yrdln":"SF 16","team":"SF"},"result":"Punt","penyds":0,"postime":"1:01","posteam":"SF","numplays":7,"ydsgained":18},"8":{"qtr":2,"fds":0,"plays":{"1407":{"sp":0,"desc":"P.Dawson kicks 56 yards from SF 35 to CHI 9. D.Thompson to CHI 37 for 28 yards (J.Ward). FUMBLES (J.Ward), RECOVERED by SF-J.Ward at CHI 37. J.Ward to CHI 37 for no gain (D.Thompson). The Replay Official reviewed the fumble ruling, and the play was Upheld. The ruling on the field stands.","qtr":2,"down":0,"players":{"00-0004091":[{"statId":41,"yards":56,"clubcode":"SF","sequence":1,"playerName":"P.Dawson"}],"00-0029388":[{"statId":45,"yards":28,"clubcode":"CHI","sequence":2,"playerName":"D.Thompson"},{"statId":52,"yards":0,"clubcode":"CHI","sequence":4,"playerName":"D.Thompson"},{"statId":106,"yards":0,"clubcode":"CHI","sequence":5,"playerName":"D.Thompson"},{"statId":79,"yards":0,"clubcode":"CHI","sequence":8,"playerName":"D.Thompson"}],"00-0031298":[{"statId":79,"yards":0,"clubcode":"SF","sequence":3,"playerName":"J.Ward"},{"statId":91,"yards":0,"clubcode":"SF","sequence":6,"playerName":"J.Ward"},{"statId":59,"yards":0,"clubcode":"SF","sequence":7,"playerName":"J.Ward"}]},"ydsnet":0,"posteam":"SF","time":"06:55","ydstogo":0,"yrdln":"SF 35","note":"FUMBLE"}},"redzone":true,"end":{"qtr":2,"time":"06:47","yrdln":"","team":"CHI"},"start":{"qtr":2,"time":"06:55","yrdln":"","team":"CHI"},"result":"Fumble","penyds":0,"postime":"0:08","posteam":"CHI","numplays":1,"ydsgained":0},"10":{"qtr":2,"fds":6,"plays":{"1770":{"sp":0,"desc":"Timeout #1 by SF at 01:48.","qtr":2,"down":0,"players":{"0":[{"statId":68,"yards":0,"clubcode":"SF","sequence":1,"playerName":""}]},"ydsnet":1,"posteam":"","time":"01:48","ydstogo":0,"yrdln":"","note":"TIMEOUT"},"1749":{"sp":0,"desc":"(1:52) (Shotgun) J.Howard right tackle to CHI 20 for 1 yard (N.Bellore).","qtr":2,"down":1,"players":{"00-0028292":[{"statId":79,"yards":0,"clubcode":"SF","sequence":2,"playerName":"N.Bellore"}],"00-0032780":[{"statId":10,"yards":1,"clubcode":"CHI","sequence":1,"playerName":"J.Howard"}]},"ydsnet":1,"posteam":"CHI","time":"01:52","ydstogo":10,"yrdln":"CHI 19","note":null},"2022":{"sp":1,"desc":"C.Barth extra point is GOOD, Center-P.Scales, Holder-P.O'Donnell.","qtr":2,"down":0,"players":{"00-0026138":[{"statId":72,"yards":0,"clubcode":"CHI","sequence":1,"playerName":"C.Barth"}]},"ydsnet":81,"posteam":"CHI","time":"00:31","ydstogo":0,"yrdln":"SF 15","note":"XP"},"1849":{"sp":0,"desc":"(1:21) (No Huddle, Shotgun) M.Barkley pass short left to D.Thompson pushed ob at CHI 43 for 11 yards (T.Brock).","qtr":2,"down":1,"players":{"00-0030533":[{"statId":15,"yards":11,"clubcode":"CHI","sequence":2,"playerName":"M.Barkley"},{"statId":111,"yards":10,"clubcode":"CHI","sequence":3,"playerName":"M.Barkley"}],"0":[{"statId":4,"yards":0,"clubcode":"CHI","sequence":1,"playerName":""}],"00-0027375":[{"statId":79,"yards":0,"clubcode":"SF","sequence":7,"playerName":"T.Brock"}],"00-0029388":[{"statId":21,"yards":11,"clubcode":"CHI","sequence":4,"playerName":"D.Thompson"},{"statId":115,"yards":0,"clubcode":"CHI","sequence":5,"playerName":"D.Thompson"},{"statId":113,"yards":1,"clubcode":"CHI","sequence":6,"playerName":"D.Thompson"}]},"ydsnet":81,"posteam":"CHI","time":"01:21","ydstogo":10,"yrdln":"CHI 32","note":null},"1966":{"sp":0,"desc":"(:39) (Shotgun) M.Barkley pass incomplete short middle to D.Brown [J.Ward]. PENALTY on SF-T.Brock, Defensive Pass Interference, 11 yards, enforced at SF 12 - No Play.","qtr":2,"down":1,"players":{"0":[{"statId":5,"yards":0,"clubcode":"CHI","sequence":1,"playerName":""}],"00-0027375":[{"statId":93,"yards":11,"clubcode":"SF","sequence":2,"playerName":"T.Brock"}]},"ydsnet":80,"posteam":"CHI","time":"00:39","ydstogo":10,"yrdln":"SF 12","note":"PENALTY"},"1949":{"sp":0,"desc":"Timeout #2 by CHI at 00:47.","qtr":2,"down":0,"players":{"0":[{"statId":68,"yards":0,"clubcode":"CHI","sequence":1,"playerName":""}]},"ydsnet":69,"posteam":"","time":"00:47","ydstogo":0,"yrdln":"","note":"TIMEOUT"},"1825":{"sp":0,"desc":"(1:43) (Shotgun) M.Barkley pass short left to D.Thompson to CHI 32 for 8 yards (T.Brock).","qtr":2,"down":3,"players":{"00-0030533":[{"statId":15,"yards":8,"clubcode":"CHI","sequence":3,"playerName":"M.Barkley"},{"statId":111,"yards":8,"clubcode":"CHI","sequence":4,"playerName":"M.Barkley"}],"0":[{"statId":4,"yards":0,"clubcode":"CHI","sequence":1,"playerName":""},{"statId":6,"yards":0,"clubcode":"CHI","sequence":2,"playerName":""}],"00-0027375":[{"statId":79,"yards":0,"clubcode":"SF","sequence":8,"playerName":"T.Brock"}],"00-0029388":[{"statId":21,"yards":8,"clubcode":"CHI","sequence":5,"playerName":"D.Thompson"},{"statId":115,"yards":0,"clubcode":"CHI","sequence":6,"playerName":"D.Thompson"},{"statId":113,"yards":0,"clubcode":"CHI","sequence":7,"playerName":"D.Thompson"}]},"ydsnet":13,"posteam":"CHI","time":"01:43","ydstogo":5,"yrdln":"CHI 24","note":null},"1726":{"sp":0,"desc":"P.Dawson kicks 51 yards from SF 35 to CHI 14. P.Lasike to CHI 19 for 5 yards (A.Burbridge).","qtr":2,"down":0,"players":{"00-0004091":[{"statId":41,"yards":51,"clubcode":"SF","sequence":1,"playerName":"P.Dawson"},{"statId":42,"yards":0,"clubcode":"SF","sequence":3,"playerName":"P.Dawson"}],"00-0031706":[{"statId":45,"yards":5,"clubcode":"CHI","sequence":2,"playerName":"P.Lasike"}],"00-0032441":[{"statId":79,"yards":0,"clubcode":"SF","sequence":4,"playerName":"A.Burbridge"}]},"ydsnet":0,"posteam":"SF","time":"01:56","ydstogo":0,"yrdln":"SF 35","note":"KICKOFF"},"1787":{"sp":0,"desc":"(1:48) (Shotgun) J.Howard right guard to CHI 24 for 4 yards (M.Wilhoite).","qtr":2,"down":2,"players":{"00-0032780":[{"statId":10,"yards":4,"clubcode":"CHI","sequence":1,"playerName":"J.Howard"}],"00-0028836":[{"statId":79,"yards":0,"clubcode":"SF","sequence":2,"playerName":"M.Wilhoite"}]},"ydsnet":5,"posteam":"CHI","time":"01:48","ydstogo":9,"yrdln":"CHI 20","note":null},"1924":{"sp":0,"desc":"(:47) (Shotgun) M.Barkley pass short right to C.Meredith to SF 12 for 17 yards (J.Ward).","qtr":2,"down":2,"players":{"00-0030533":[{"statId":15,"yards":17,"clubcode":"CHI","sequence":2,"playerName":"M.Barkley"},{"statId":111,"yards":14,"clubcode":"CHI","sequence":3,"playerName":"M.Barkley"}],"00-0031298":[{"statId":79,"yards":0,"clubcode":"SF","sequence":7,"playerName":"J.Ward"}],"0":[{"statId":4,"yards":0,"clubcode":"CHI","sequence":1,"playerName":""}],"00-0031912":[{"statId":21,"yards":17,"clubcode":"CHI","sequence":4,"playerName":"C.Meredith"},{"statId":115,"yards":0,"clubcode":"CHI","sequence":5,"playerName":"C.Meredith"},{"statId":113,"yards":3,"clubcode":"CHI","sequence":6,"playerName":"C.Meredith"}]},"ydsnet":69,"posteam":"CHI","time":"00:47","ydstogo":10,"yrdln":"SF 29","note":null},"1999":{"sp":1,"desc":"(:35) J.Howard left tackle for 1 yard, TOUCHDOWN.","qtr":2,"down":1,"players":{"00-0032780":[{"statId":11,"yards":1,"clubcode":"CHI","sequence":2,"playerName":"J.Howard"}],"0":[{"statId":3,"yards":0,"clubcode":"CHI","sequence":1,"playerName":""}]},"ydsnet":81,"posteam":"CHI","time":"00:35","ydstogo":1,"yrdln":"SF 1","note":"TD"},"1902":{"sp":0,"desc":"(:51) (No Huddle, Shotgun) M.Barkley pass incomplete short right to D.Thompson.","qtr":2,"down":1,"players":{"00-0030533":[{"statId":14,"yards":0,"clubcode":"CHI","sequence":1,"playerName":"M.Barkley"},{"statId":112,"yards":9,"clubcode":"CHI","sequence":3,"playerName":"M.Barkley"}],"00-0029388":[{"statId":115,"yards":0,"clubcode":"CHI","sequence":2,"playerName":"D.Thompson"}]},"ydsnet":52,"posteam":"CHI","time":"00:51","ydstogo":10,"yrdln":"SF 29","note":null},"1808":{"sp":0,"desc":"Timeout #2 by SF at 01:43.","qtr":2,"down":0,"players":{"0":[{"statId":68,"yards":0,"clubcode":"SF","sequence":1,"playerName":""}]},"ydsnet":5,"posteam":"","time":"01:43","ydstogo":0,"yrdln":"","note":"TIMEOUT"},"1878":{"sp":0,"desc":"(1:16) (Shotgun) M.Barkley pass deep middle to C.Meredith to SF 29 for 28 yards (A.Bethea).","qtr":2,"down":1,"players":{"00-0030533":[{"statId":15,"yards":28,"clubcode":"CHI","sequence":2,"playerName":"M.Barkley"},{"statId":111,"yards":17,"clubcode":"CHI","sequence":3,"playerName":"M.Barkley"}],"00-0024421":[{"statId":79,"yards":0,"clubcode":"SF","sequence":7,"playerName":"A.Bethea"}],"0":[{"statId":4,"yards":0,"clubcode":"CHI","sequence":1,"playerName":""}],"00-0031912":[{"statId":21,"yards":28,"clubcode":"CHI","sequence":4,"playerName":"C.Meredith"},{"statId":115,"yards":0,"clubcode":"CHI","sequence":5,"playerName":"C.Meredith"},{"statId":113,"yards":11,"clubcode":"CHI","sequence":6,"playerName":"C.Meredith"}]},"ydsnet":81,"posteam":"CHI","time":"01:16","ydstogo":10,"yrdln":"CHI 43","note":null}},"redzone":true,"end":{"qtr":2,"time":"00:31","yrdln":"SF 1","team":"CHI"},"start":{"qtr":2,"time":"01:56","yrdln":"CHI 19","team":"CHI"},"result":"Touchdown","penyds":11,"postime":"1:25","posteam":"CHI","numplays":14,"ydsgained":70},"6":{"qtr":2,"fds":1,"plays":{"1230":{"sp":0,"desc":"(9:18) (Punt formation) PENALTY on CHI-P.O'Donnell, Delay of Game, 5 yards, enforced at CHI 19 - No Play.","qtr":2,"down":4,"players":{"00-0031079":[{"statId":93,"yards":5,"clubcode":"CHI","sequence":1,"playerName":"P.O'Donnell"}]},"ydsnet":9,"posteam":"CHI","time":"09:18","ydstogo":7,"yrdln":"CHI 19","note":"PENALTY"},"1126":{"sp":0,"desc":"(11:11) M.Barkley pass short right to C.Meredith to CHI 31 for 15 yards (A.Bethea). PENALTY on CHI-C.Leno, Ineligible Downfield Pass, 5 yards, enforced at CHI 16 - No Play.","qtr":2,"down":1,"players":{"00-0031095":[{"statId":93,"yards":5,"clubcode":"CHI","sequence":1,"playerName":"C.Leno"}]},"ydsnet":9,"posteam":"CHI","time":"11:11","ydstogo":10,"yrdln":"CHI 16","note":"PENALTY"},"1208":{"sp":0,"desc":"(9:23) (Shotgun) M.Barkley pass incomplete short right to J.Bellamy.","qtr":2,"down":3,"players":{"00-0030533":[{"statId":14,"yards":0,"clubcode":"CHI","sequence":2,"playerName":"M.Barkley"},{"statId":112,"yards":11,"clubcode":"CHI","sequence":4,"playerName":"M.Barkley"}],"0":[{"statId":7,"yards":0,"clubcode":"CHI","sequence":1,"playerName":""}],"00-0029319":[{"statId":115,"yards":0,"clubcode":"CHI","sequence":3,"playerName":"J.Bellamy"}]},"ydsnet":14,"posteam":"CHI","time":"09:23","ydstogo":7,"yrdln":"CHI 19","note":null},"1161":{"sp":0,"desc":"(10:42) K.Carey left end pushed ob at CHI 15 for 4 yards (D.Buckner).","qtr":2,"down":1,"players":{"00-0032378":[{"statId":79,"yards":0,"clubcode":"SF","sequence":2,"playerName":"D.Buckner"}],"00-0031057":[{"statId":10,"yards":4,"clubcode":"CHI","sequence":1,"playerName":"K.Carey"}]},"ydsnet":10,"posteam":"CHI","time":"10:42","ydstogo":15,"yrdln":"CHI 11","note":null},"1105":{"sp":0,"desc":"(11:47) J.Howard left tackle to CHI 16 for 3 yards (C.Jones).","qtr":2,"down":3,"players":{"00-0032780":[{"statId":10,"yards":3,"clubcode":"CHI","sequence":3,"playerName":"J.Howard"}],"0":[{"statId":3,"yards":0,"clubcode":"CHI","sequence":1,"playerName":""},{"statId":6,"yards":0,"clubcode":"CHI","sequence":2,"playerName":""}],"00-0030106":[{"statId":79,"yards":0,"clubcode":"SF","sequence":4,"playerName":"C.Jones"}]},"ydsnet":11,"posteam":"CHI","time":"11:47","ydstogo":2,"yrdln":"CHI 13","note":null},"1187":{"sp":0,"desc":"(10:07) K.Carey left guard to CHI 19 for 4 yards (N.Bellore; G.Dorsey).","qtr":2,"down":2,"players":{"00-0028292":[{"statId":82,"yards":0,"clubcode":"SF","sequence":2,"playerName":"N.Bellore"}],"00-0031057":[{"statId":10,"yards":4,"clubcode":"CHI","sequence":1,"playerName":"K.Carey"}],"00-0026145":[{"statId":82,"yards":0,"clubcode":"SF","sequence":3,"playerName":"G.Dorsey"}]},"ydsnet":14,"posteam":"CHI","time":"10:07","ydstogo":11,"yrdln":"CHI 15","note":null},"1257":{"sp":0,"desc":"(9:18) (Punt formation) P.O'Donnell punts 15 yards to CHI 29, Center-P.Scales. D.Johnson pushed ob at CHI 4 for 25 yards (B.Braunecker). PENALTY on SF-R.Robinson, Unsportsmanlike Conduct, 15 yards, enforced at CHI 4.","qtr":2,"down":4,"players":{"00-0032661":[{"statId":79,"yards":0,"clubcode":"CHI","sequence":3,"playerName":"B.Braunecker"}],"00-0032410":[{"statId":93,"yards":15,"clubcode":"SF","sequence":4,"playerName":"R.Robinson"}],"00-0031061":[{"statId":33,"yards":25,"clubcode":"SF","sequence":2,"playerName":"D.Johnson"}],"00-0031079":[{"statId":29,"yards":15,"clubcode":"CHI","sequence":1,"playerName":"P.O'Donnell"}]},"ydsnet":9,"posteam":"CHI","time":"09:18","ydstogo":12,"yrdln":"CHI 14","note":"PUNT"},"1084":{"sp":0,"desc":"(12:32) J.Howard right guard to CHI 13 for 4 yards (G.Dorsey).","qtr":2,"down":2,"players":{"00-0032780":[{"statId":10,"yards":4,"clubcode":"CHI","sequence":1,"playerName":"J.Howard"}],"00-0026145":[{"statId":79,"yards":0,"clubcode":"SF","sequence":2,"playerName":"G.Dorsey"}]},"ydsnet":8,"posteam":"CHI","time":"12:32","ydstogo":6,"yrdln":"CHI 9","note":null},"1063":{"sp":0,"desc":"(13:11) J.Howard right end to CHI 9 for 4 yards (G.Hodges).","qtr":2,"down":1,"players":{"00-0032780":[{"statId":10,"yards":4,"clubcode":"CHI","sequence":1,"playerName":"J.Howard"}],"00-0030385":[{"statId":79,"yards":0,"clubcode":"SF","sequence":2,"playerName":"G.Hodges"}]},"ydsnet":4,"posteam":"CHI","time":"13:11","ydstogo":10,"yrdln":"CHI 5","note":null}},"redzone":true,"end":{"qtr":2,"time":"09:07","yrdln":"CHI 14","team":"CHI"},"start":{"qtr":2,"time":"13:11","yrdln":"CHI 5","team":"CHI"},"result":"Punt","penyds":-10,"postime":"4:04","posteam":"CHI","numplays":9,"ydsgained":19},"18":{"qtr":4,"fds":2,"plays":{"3208":{"sp":1,"desc":"(13:01) (Field Goal formation) C.Barth 45 yard field goal is GOOD, Center-P.Scales, Holder-P.O'Donnell.","qtr":4,"down":4,"players":{"00-0026138":[{"statId":70,"yards":45,"clubcode":"CHI","sequence":1,"playerName":"C.Barth"}]},"ydsnet":37,"posteam":"CHI","time":"13:01","ydstogo":16,"yrdln":"SF 27","note":"FG"},"3189":{"sp":0,"desc":"(13:46) (Shotgun) M.Barkley sacked at SF 27 for -8 yards (A.Brooks).","qtr":4,"down":3,"players":{"00-0024495":[{"statId":83,"yards":-8,"clubcode":"SF","sequence":3,"playerName":"A.Brooks"},{"statId":110,"yards":0,"clubcode":"SF","sequence":4,"playerName":"A.Brooks"},{"statId":79,"yards":0,"clubcode":"SF","sequence":5,"playerName":"A.Brooks"},{"statId":120,"yards":0,"clubcode":"SF","sequence":6,"playerName":"A.Brooks"},{"statId":402,"yards":8,"clubcode":"SF","sequence":7,"playerName":"A.Brooks"}],"00-0030533":[{"statId":20,"yards":-8,"clubcode":"CHI","sequence":2,"playerName":"M.Barkley"}],"0":[{"statId":7,"yards":0,"clubcode":"CHI","sequence":1,"playerName":""}]},"ydsnet":37,"posteam":"CHI","time":"13:46","ydstogo":8,"yrdln":"SF 19","note":null},"2997":{"sp":0,"desc":"(1:14) M.Barkley pass deep right to D.Thompson to SF 33 for 31 yards (A.Bethea). PENALTY on CHI-D.Thompson, Offensive Pass Interference, 10 yards, enforced at CHI 36 - No Play.","qtr":3,"down":1,"players":{"00-0029388":[{"statId":93,"yards":10,"clubcode":"CHI","sequence":1,"playerName":"D.Thompson"}]},"ydsnet":-10,"posteam":"CHI","time":"01:14","ydstogo":10,"yrdln":"CHI 36","note":"PENALTY"},"3067":{"sp":0,"desc":"(:35) (Shotgun) J.Howard left tackle to SF 33 for 25 yards (G.Hodges).","qtr":3,"down":2,"players":{"00-0032780":[{"statId":10,"yards":25,"clubcode":"CHI","sequence":2,"playerName":"J.Howard"}],"0":[{"statId":3,"yards":0,"clubcode":"CHI","sequence":1,"playerName":""}],"00-0030385":[{"statId":79,"yards":0,"clubcode":"SF","sequence":3,"playerName":"G.Hodges"}]},"ydsnet":31,"posteam":"CHI","time":"00:35","ydstogo":4,"yrdln":"CHI 42","note":null},"3167":{"sp":0,"desc":"(13:51) (Shotgun) M.Barkley pass incomplete short right to C.Meredith.","qtr":4,"down":2,"players":{"00-0030533":[{"statId":14,"yards":0,"clubcode":"CHI","sequence":1,"playerName":"M.Barkley"},{"statId":112,"yards":0,"clubcode":"CHI","sequence":3,"playerName":"M.Barkley"}],"00-0031912":[{"statId":115,"yards":0,"clubcode":"CHI","sequence":2,"playerName":"C.Meredith"}]},"ydsnet":45,"posteam":"CHI","time":"13:51","ydstogo":8,"yrdln":"SF 19","note":null},"3146":{"sp":0,"desc":"Timeout at 13:59.","qtr":4,"down":0,"players":{},"ydsnet":45,"posteam":"","time":"13:59","ydstogo":0,"yrdln":"","note":"Timeout"},"3032":{"sp":0,"desc":"(:54) M.Barkley pass short middle to J.Bellamy to CHI 42 for 16 yards (N.Bellore). Penalty on SF-G.Dorsey, Defensive Offside, declined.","qtr":3,"down":1,"players":{"00-0028292":[{"statId":79,"yards":0,"clubcode":"SF","sequence":6,"playerName":"N.Bellore"}],"00-0030533":[{"statId":15,"yards":16,"clubcode":"CHI","sequence":1,"playerName":"M.Barkley"},{"statId":111,"yards":14,"clubcode":"CHI","sequence":2,"playerName":"M.Barkley"}],"00-0029319":[{"statId":21,"yards":16,"clubcode":"CHI","sequence":3,"playerName":"J.Bellamy"},{"statId":115,"yards":0,"clubcode":"CHI","sequence":4,"playerName":"J.Bellamy"},{"statId":113,"yards":2,"clubcode":"CHI","sequence":5,"playerName":"J.Bellamy"}]},"ydsnet":6,"posteam":"CHI","time":"00:54","ydstogo":20,"yrdln":"CHI 26","note":null},"3125":{"sp":0,"desc":"(14:12) J.Howard right guard to SF 19 for 2 yards (N.Bellore). CHI-C.Whitehair was injured during the play.","qtr":4,"down":1,"players":{"00-0028292":[{"statId":79,"yards":0,"clubcode":"SF","sequence":2,"playerName":"N.Bellore"}],"00-0032780":[{"statId":10,"yards":2,"clubcode":"CHI","sequence":1,"playerName":"J.Howard"}]},"ydsnet":45,"posteam":"CHI","time":"14:12","ydstogo":10,"yrdln":"SF 21","note":null},"3088":{"sp":0,"desc":"END QUARTER 3","qtr":3,"down":0,"players":{},"ydsnet":31,"posteam":"","time":"","ydstogo":0,"yrdln":"","note":null},"3104":{"sp":0,"desc":"(15:00) J.Bellamy left end to SF 21 for 12 yards (J.Tartt).","qtr":4,"down":1,"players":{"00-0032057":[{"statId":79,"yards":0,"clubcode":"SF","sequence":3,"playerName":"J.Tartt"}],"0":[{"statId":3,"yards":0,"clubcode":"CHI","sequence":1,"playerName":""}],"00-0029319":[{"statId":10,"yards":12,"clubcode":"CHI","sequence":2,"playerName":"J.Bellamy"}]},"ydsnet":43,"posteam":"CHI","time":"15:00","ydstogo":10,"yrdln":"SF 33","note":null}},"redzone":true,"end":{"qtr":3,"time":"12:55","yrdln":"SF 27","team":"CHI"},"start":{"qtr":3,"time":"01:14","yrdln":"CHI 36","team":"CHI"},"result":"Field Goal","penyds":-10,"postime":"3:19","posteam":"CHI","numplays":10,"ydsgained":47},"16":{"qtr":3,"fds":0,"plays":{"2820":{"sp":0,"desc":"(4:22) J.Howard left tackle to CHI 39 for 4 yards (N.Bellore).","qtr":3,"down":1,"players":{"00-0028292":[{"statId":79,"yards":0,"clubcode":"SF","sequence":2,"playerName":"N.Bellore"}],"00-0032780":[{"statId":10,"yards":4,"clubcode":"CHI","sequence":1,"playerName":"J.Howard"}]},"ydsnet":4,"posteam":"CHI","time":"04:22","ydstogo":10,"yrdln":"CHI 35","note":null},"2862":{"sp":0,"desc":"(3:09) (Shotgun) M.Barkley pass incomplete deep middle to J.Bellamy.","qtr":3,"down":3,"players":{"00-0030533":[{"statId":14,"yards":0,"clubcode":"CHI","sequence":2,"playerName":"M.Barkley"},{"statId":112,"yards":31,"clubcode":"CHI","sequence":4,"playerName":"M.Barkley"}],"0":[{"statId":7,"yards":0,"clubcode":"CHI","sequence":1,"playerName":""}],"00-0029319":[{"statId":115,"yards":0,"clubcode":"CHI","sequence":3,"playerName":"J.Bellamy"}]},"ydsnet":4,"posteam":"CHI","time":"03:09","ydstogo":6,"yrdln":"CHI 39","note":null},"2884":{"sp":0,"desc":"(3:03) (Punt formation) P.O'Donnell punts 46 yards to SF 15, Center-P.Scales, fair catch by J.Kerley.","qtr":3,"down":4,"players":{"00-0028091":[{"statId":39,"yards":0,"clubcode":"SF","sequence":3,"playerName":"J.Kerley"}],"00-0031079":[{"statId":29,"yards":46,"clubcode":"CHI","sequence":1,"playerName":"P.O'Donnell"},{"statId":30,"yards":0,"clubcode":"CHI","sequence":2,"playerName":"P.O'Donnell"}]},"ydsnet":4,"posteam":"CHI","time":"03:03","ydstogo":6,"yrdln":"CHI 39","note":"PUNT"},"2841":{"sp":0,"desc":"(3:48) J.Howard left guard to CHI 39 for no gain (N.Bellore).","qtr":3,"down":2,"players":{"00-0028292":[{"statId":79,"yards":0,"clubcode":"SF","sequence":2,"playerName":"N.Bellore"}],"00-0032780":[{"statId":10,"yards":0,"clubcode":"CHI","sequence":1,"playerName":"J.Howard"}]},"ydsnet":4,"posteam":"CHI","time":"03:48","ydstogo":6,"yrdln":"CHI 39","note":null}},"redzone":true,"end":{"qtr":3,"time":"02:55","yrdln":"CHI 39","team":"CHI"},"start":{"qtr":3,"time":"04:22","yrdln":"CHI 35","team":"CHI"},"result":"Punt","penyds":0,"postime":"1:27","posteam":"CHI","numplays":4,"ydsgained":4},"21":{"qtr":4,"fds":1,"plays":{"3592":{"sp":0,"desc":"(7:30) (No Huddle, Shotgun) B.Gabbert pass incomplete short left to C.Harper (N.Kwiatkoski).","qtr":4,"down":2,"players":{"00-0031854":[{"statId":115,"yards":0,"clubcode":"SF","sequence":2,"playerName":"C.Harper"}],"00-0027948":[{"statId":14,"yards":0,"clubcode":"SF","sequence":1,"playerName":"B.Gabbert"},{"statId":112,"yards":4,"clubcode":"SF","sequence":4,"playerName":"B.Gabbert"}],"00-0032773":[{"statId":85,"yards":0,"clubcode":"CHI","sequence":3,"playerName":"N.Kwiatkoski"}]},"ydsnet":6,"posteam":"SF","time":"07:30","ydstogo":4,"yrdln":"SF 16","note":null},"3614":{"sp":0,"desc":"(7:22) (No Huddle, Shotgun) B.Gabbert pass short right to C.Harper to SF 22 for 6 yards (N.Kwiatkoski).","qtr":4,"down":3,"players":{"00-0031854":[{"statId":21,"yards":6,"clubcode":"SF","sequence":5,"playerName":"C.Harper"},{"statId":115,"yards":0,"clubcode":"SF","sequence":6,"playerName":"C.Harper"},{"statId":113,"yards":1,"clubcode":"SF","sequence":7,"playerName":"C.Harper"}],"00-0027948":[{"statId":15,"yards":6,"clubcode":"SF","sequence":3,"playerName":"B.Gabbert"},{"statId":111,"yards":5,"clubcode":"SF","sequence":4,"playerName":"B.Gabbert"}],"0":[{"statId":4,"yards":0,"clubcode":"SF","sequence":1,"playerName":""},{"statId":6,"yards":0,"clubcode":"SF","sequence":2,"playerName":""}],"00-0032773":[{"statId":79,"yards":0,"clubcode":"CHI","sequence":8,"playerName":"N.Kwiatkoski"}]},"ydsnet":12,"posteam":"SF","time":"07:22","ydstogo":4,"yrdln":"SF 16","note":null},"3701":{"sp":0,"desc":"(5:48) (No Huddle, Shotgun) B.Gabbert pass incomplete short right to S.Draughn (N.Kwiatkoski).","qtr":4,"down":2,"players":{"00-0028202":[{"statId":115,"yards":0,"clubcode":"SF","sequence":2,"playerName":"S.Draughn"}],"00-0027948":[{"statId":14,"yards":0,"clubcode":"SF","sequence":1,"playerName":"B.Gabbert"},{"statId":112,"yards":0,"clubcode":"SF","sequence":4,"playerName":"B.Gabbert"}],"00-0032773":[{"statId":85,"yards":0,"clubcode":"CHI","sequence":3,"playerName":"N.Kwiatkoski"}]},"ydsnet":3,"posteam":"SF","time":"05:48","ydstogo":19,"yrdln":"SF 13","note":null},"3638":{"sp":0,"desc":"(6:52) (No Huddle, Shotgun) B.Gabbert scrambles left tackle ran ob at SF 30 for 8 yards. PENALTY on SF-D.Kilgore, Offensive Holding, 10 yards, enforced at SF 22 - No Play.","qtr":4,"down":1,"players":{"00-0028101":[{"statId":93,"yards":10,"clubcode":"SF","sequence":1,"playerName":"D.Kilgore"}]},"ydsnet":2,"posteam":"SF","time":"06:52","ydstogo":10,"yrdln":"SF 22","note":"PENALTY"},"3723":{"sp":0,"desc":"(5:44) (No Huddle, Shotgun) B.Gabbert pass incomplete deep right to T.Smith.","qtr":4,"down":3,"players":{"00-0027996":[{"statId":115,"yards":0,"clubcode":"SF","sequence":3,"playerName":"T.Smith"}],"00-0027948":[{"statId":14,"yards":0,"clubcode":"SF","sequence":2,"playerName":"B.Gabbert"},{"statId":112,"yards":17,"clubcode":"SF","sequence":4,"playerName":"B.Gabbert"}],"0":[{"statId":7,"yards":0,"clubcode":"SF","sequence":1,"playerName":""}]},"ydsnet":3,"posteam":"SF","time":"05:44","ydstogo":19,"yrdln":"SF 13","note":null},"3745":{"sp":0,"desc":"(5:39) (Punt formation) B.Pinion punts 41 yards to CHI 46, Center-K.Nelson, fair catch by B.Callahan.","qtr":4,"down":4,"players":{"00-0032065":[{"statId":29,"yards":41,"clubcode":"SF","sequence":1,"playerName":"B.Pinion"}],"00-0031904":[{"statId":39,"yards":0,"clubcode":"CHI","sequence":2,"playerName":"B.Callahan"}]},"ydsnet":3,"posteam":"SF","time":"05:39","ydstogo":19,"yrdln":"SF 13","note":"PUNT"},"3675":{"sp":0,"desc":"(6:24) (No Huddle, Shotgun) B.Gabbert scrambles right end pushed ob at SF 13 for 1 yard (T.Porter).","qtr":4,"down":1,"players":{"00-0027948":[{"statId":10,"yards":1,"clubcode":"SF","sequence":1,"playerName":"B.Gabbert"}],"00-0026180":[{"statId":79,"yards":0,"clubcode":"CHI","sequence":2,"playerName":"T.Porter"}]},"ydsnet":3,"posteam":"SF","time":"06:24","ydstogo":20,"yrdln":"SF 12","note":null},"3568":{"sp":0,"desc":"(8:05) (Shotgun) B.Gabbert pass short right to C.Hyde to SF 16 for 6 yards (H.Jones-Quartey).","qtr":4,"down":1,"players":{"00-0027948":[{"statId":15,"yards":6,"clubcode":"SF","sequence":1,"playerName":"B.Gabbert"},{"statId":111,"yards":4,"clubcode":"SF","sequence":2,"playerName":"B.Gabbert"}],"00-0031989":[{"statId":79,"yards":0,"clubcode":"CHI","sequence":6,"playerName":"H.Jones-Quartey"}],"00-0031045":[{"statId":21,"yards":6,"clubcode":"SF","sequence":3,"playerName":"C.Hyde"},{"statId":115,"yards":0,"clubcode":"SF","sequence":4,"playerName":"C.Hyde"},{"statId":113,"yards":2,"clubcode":"SF","sequence":5,"playerName":"C.Hyde"}]},"ydsnet":6,"posteam":"SF","time":"08:05","ydstogo":10,"yrdln":"SF 10","note":null}},"redzone":true,"end":{"qtr":4,"time":"05:31","yrdln":"SF 13","team":"SF"},"start":{"qtr":4,"time":"08:05","yrdln":"SF 10","team":"SF"},"result":"Punt","penyds":-10,"postime":"2:34","posteam":"SF","numplays":8,"ydsgained":13},"5":{"qtr":2,"fds":4,"plays":{"805":{"sp":0,"desc":"(2:54) (No Huddle, Shotgun) C.Hyde left end to CHI 45 for 1 yard (J.Timu).","qtr":1,"down":2,"players":{"00-0031915":[{"statId":79,"yards":0,"clubcode":"CHI","sequence":2,"playerName":"J.Timu"}],"00-0031045":[{"statId":10,"yards":1,"clubcode":"SF","sequence":1,"playerName":"C.Hyde"}]},"ydsnet":43,"posteam":"SF","time":"02:54","ydstogo":2,"yrdln":"CHI 46","note":null},"916":{"sp":0,"desc":"END QUARTER 1","qtr":1,"down":0,"players":{},"ydsnet":55,"posteam":"","time":"","ydstogo":0,"yrdln":"","note":null},"1005":{"sp":0,"desc":"(13:53) (Shotgun) C.Hyde right guard to CHI 31 for 7 yards (C.Washington).","qtr":2,"down":3,"players":{"00-0030048":[{"statId":79,"yards":0,"clubcode":"CHI","sequence":3,"playerName":"C.Washington"}],"0":[{"statId":7,"yards":0,"clubcode":"SF","sequence":1,"playerName":""}],"00-0031045":[{"statId":10,"yards":7,"clubcode":"SF","sequence":2,"playerName":"C.Hyde"}]},"ydsnet":57,"posteam":"SF","time":"13:53","ydstogo":16,"yrdln":"CHI 38","note":null},"873":{"sp":0,"desc":"(1:08) (No Huddle, Shotgun) S.Draughn right guard to CHI 32 for 5 yards (A.Hicks; H.Jones-Quartey).","qtr":1,"down":2,"players":{"00-0029657":[{"statId":82,"yards":0,"clubcode":"CHI","sequence":3,"playerName":"A.Hicks"}],"00-0028202":[{"statId":10,"yards":5,"clubcode":"SF","sequence":2,"playerName":"S.Draughn"}],"0":[{"statId":3,"yards":0,"clubcode":"SF","sequence":1,"playerName":""}],"00-0031989":[{"statId":82,"yards":0,"clubcode":"CHI","sequence":4,"playerName":"H.Jones-Quartey"}]},"ydsnet":56,"posteam":"SF","time":"01:08","ydstogo":4,"yrdln":"CHI 37","note":null},"847":{"sp":0,"desc":"(1:40) (No Huddle, Shotgun) C.Kaepernick left end pushed ob at CHI 37 for 6 yards (H.Jones-Quartey).","qtr":1,"down":1,"players":{"00-0027974":[{"statId":10,"yards":6,"clubcode":"SF","sequence":1,"playerName":"C.Kaepernick"}],"00-0031989":[{"statId":79,"yards":0,"clubcode":"CHI","sequence":2,"playerName":"H.Jones-Quartey"}]},"ydsnet":51,"posteam":"SF","time":"01:40","ydstogo":10,"yrdln":"CHI 43","note":null},"659":{"sp":0,"desc":"(5:52) (Shotgun) C.Hyde left guard to SF 15 for 3 yards (J.Timu).","qtr":1,"down":1,"players":{"00-0031915":[{"statId":79,"yards":0,"clubcode":"CHI","sequence":2,"playerName":"J.Timu"}],"00-0031045":[{"statId":10,"yards":3,"clubcode":"SF","sequence":1,"playerName":"C.Hyde"}]},"ydsnet":3,"posteam":"SF","time":"05:52","ydstogo":10,"yrdln":"SF 12","note":null},"826":{"sp":0,"desc":"(2:15) (No Huddle, Shotgun) S.Draughn right guard to CHI 43 for 2 yards (A.Hicks).","qtr":1,"down":3,"players":{"00-0029657":[{"statId":79,"yards":0,"clubcode":"CHI","sequence":4,"playerName":"A.Hicks"}],"00-0028202":[{"statId":10,"yards":2,"clubcode":"SF","sequence":3,"playerName":"S.Draughn"}],"0":[{"statId":3,"yards":0,"clubcode":"SF","sequence":1,"playerName":""},{"statId":6,"yards":0,"clubcode":"SF","sequence":2,"playerName":""}]},"ydsnet":45,"posteam":"SF","time":"02:15","ydstogo":1,"yrdln":"CHI 45","note":null},"967":{"sp":0,"desc":"(14:30) (No Huddle, Shotgun) C.Hyde left guard to CHI 38 for 5 yards (N.Kwiatkoski).","qtr":2,"down":2,"players":{"00-0032773":[{"statId":79,"yards":0,"clubcode":"CHI","sequence":2,"playerName":"N.Kwiatkoski"}],"00-0031045":[{"statId":10,"yards":5,"clubcode":"SF","sequence":1,"playerName":"C.Hyde"}]},"ydsnet":50,"posteam":"SF","time":"14:30","ydstogo":21,"yrdln":"CHI 43","note":null},"894":{"sp":0,"desc":"(:30) (No Huddle, Shotgun) C.Hyde right tackle to CHI 33 for -1 yards (A.Hicks).","qtr":1,"down":1,"players":{"00-0029657":[{"statId":79,"yards":0,"clubcode":"CHI","sequence":3,"playerName":"A.Hicks"},{"statId":120,"yards":0,"clubcode":"CHI","sequence":4,"playerName":"A.Hicks"},{"statId":402,"yards":1,"clubcode":"CHI","sequence":5,"playerName":"A.Hicks"}],"0":[{"statId":95,"yards":-1,"clubcode":"SF","sequence":2,"playerName":""}],"00-0031045":[{"statId":10,"yards":-1,"clubcode":"SF","sequence":1,"playerName":"C.Hyde"}]},"ydsnet":55,"posteam":"SF","time":"00:30","ydstogo":10,"yrdln":"CHI 32","note":null},"1026":{"sp":0,"desc":"(13:18) (Punt formation) B.Pinion punts 26 yards to CHI 5, Center-K.Nelson, fair catch by B.Callahan.","qtr":2,"down":4,"players":{"00-0032065":[{"statId":29,"yards":26,"clubcode":"SF","sequence":1,"playerName":"B.Pinion"},{"statId":30,"yards":0,"clubcode":"SF","sequence":2,"playerName":"B.Pinion"}],"00-0031904":[{"statId":39,"yards":0,"clubcode":"CHI","sequence":3,"playerName":"B.Callahan"}]},"ydsnet":57,"posteam":"SF","time":"13:18","ydstogo":9,"yrdln":"CHI 31","note":"PUNT"},"680":{"sp":0,"desc":"(5:22) (No Huddle, Shotgun) C.Hyde left tackle to SF 27 for 12 yards (L.Floyd).","qtr":1,"down":2,"players":{"00-0033072":[{"statId":79,"yards":0,"clubcode":"CHI","sequence":3,"playerName":"L.Floyd"}],"0":[{"statId":3,"yards":0,"clubcode":"SF","sequence":1,"playerName":""}],"00-0031045":[{"statId":10,"yards":12,"clubcode":"SF","sequence":2,"playerName":"C.Hyde"}]},"ydsnet":15,"posteam":"SF","time":"05:22","ydstogo":7,"yrdln":"SF 15","note":null},"767":{"sp":0,"desc":"Timeout at 03:33.","qtr":1,"down":0,"players":{},"ydsnet":34,"posteam":"","time":"03:33","ydstogo":0,"yrdln":"","note":"Timeout"},"743":{"sp":0,"desc":"(3:41) (No Huddle, Shotgun) C.Kaepernick scrambles right tackle pushed ob at SF 46 for 14 yards (T.Porter). CHI-T.Porter was injured during the play.","qtr":1,"down":3,"players":{"0":[{"statId":3,"yards":0,"clubcode":"SF","sequence":1,"playerName":""},{"statId":6,"yards":0,"clubcode":"SF","sequence":2,"playerName":""}],"00-0027974":[{"statId":10,"yards":14,"clubcode":"SF","sequence":3,"playerName":"C.Kaepernick"}],"00-0026180":[{"statId":79,"yards":0,"clubcode":"CHI","sequence":4,"playerName":"T.Porter"}]},"ydsnet":34,"posteam":"SF","time":"03:41","ydstogo":5,"yrdln":"SF 32","note":null},"784":{"sp":0,"desc":"(3:21) (Shotgun) C.Hyde left guard to CHI 46 for 8 yards (A.Hicks).","qtr":1,"down":1,"players":{"00-0029657":[{"statId":79,"yards":0,"clubcode":"CHI","sequence":2,"playerName":"A.Hicks"}],"00-0031045":[{"statId":10,"yards":8,"clubcode":"SF","sequence":1,"playerName":"C.Hyde"}]},"ydsnet":42,"posteam":"SF","time":"03:21","ydstogo":10,"yrdln":"SF 46","note":null},"722":{"sp":0,"desc":"(4:24) (No Huddle, Shotgun) S.Draughn right guard to SF 32 for 1 yard (L.Floyd).","qtr":1,"down":2,"players":{"00-0033072":[{"statId":79,"yards":0,"clubcode":"CHI","sequence":2,"playerName":"L.Floyd"}],"00-0028202":[{"statId":10,"yards":1,"clubcode":"SF","sequence":1,"playerName":"S.Draughn"}]},"ydsnet":20,"posteam":"SF","time":"04:24","ydstogo":6,"yrdln":"SF 31","note":null},"988":{"sp":0,"desc":"Timeout #1 by CHI at 13:53.","qtr":2,"down":0,"players":{"0":[{"statId":68,"yards":0,"clubcode":"CHI","sequence":1,"playerName":""}]},"ydsnet":50,"posteam":"","time":"13:53","ydstogo":0,"yrdln":"","note":"TIMEOUT"},"701":{"sp":0,"desc":"(4:51) (Shotgun) C.Hyde right guard to SF 31 for 4 yards (N.Kwiatkoski).","qtr":1,"down":1,"players":{"00-0032773":[{"statId":79,"yards":0,"clubcode":"CHI","sequence":2,"playerName":"N.Kwiatkoski"}],"00-0031045":[{"statId":10,"yards":4,"clubcode":"SF","sequence":1,"playerName":"C.Hyde"}]},"ydsnet":19,"posteam":"SF","time":"04:51","ydstogo":10,"yrdln":"SF 27","note":null},"932":{"sp":0,"desc":"(15:00) (Shotgun) C.Kaepernick pass short middle to S.Draughn to CHI 18 for 15 yards (B.Callahan). PENALTY on SF-J.Garnett, Offensive Holding, 10 yards, enforced at CHI 33 - No Play.","qtr":2,"down":2,"players":{"00-0033151":[{"statId":93,"yards":10,"clubcode":"SF","sequence":1,"playerName":"J.Garnett"}]},"ydsnet":45,"posteam":"SF","time":"15:00","ydstogo":11,"yrdln":"CHI 33","note":"PENALTY"}},"redzone":true,"end":{"qtr":1,"time":"13:11","yrdln":"CHI 31","team":"SF"},"start":{"qtr":1,"time":"05:52","yrdln":"SF 12","team":"SF"},"result":"Punt","penyds":-10,"postime":"7:41","posteam":"SF","numplays":18,"ydsgained":67},"15":{"qtr":3,"fds":0,"plays":{"2715":{"sp":0,"desc":"(6:19) (No Huddle, Shotgun) C.Hyde right guard to SF 28 for 8 yards (C.Washington).","qtr":3,"down":1,"players":{"00-0030048":[{"statId":79,"yards":0,"clubcode":"CHI","sequence":2,"playerName":"C.Washington"}],"00-0031045":[{"statId":10,"yards":8,"clubcode":"SF","sequence":1,"playerName":"C.Hyde"}]},"ydsnet":3,"posteam":"SF","time":"06:19","ydstogo":15,"yrdln":"SF 20","note":null},"2692":{"sp":0,"desc":"(6:19) (Shotgun) PENALTY on SF-Z.Beadles, False Start, 5 yards, enforced at SF 25 - No Play.","qtr":3,"down":1,"players":{"00-0027658":[{"statId":93,"yards":5,"clubcode":"SF","sequence":1,"playerName":"Z.Beadles"}]},"ydsnet":-5,"posteam":"SF","time":"06:19","ydstogo":10,"yrdln":"SF 25","note":"PENALTY"},"2736":{"sp":0,"desc":"(5:50) (No Huddle, Shotgun) C.Kaepernick sacked ob at SF 28 for 0 yards (L.Floyd).","qtr":3,"down":2,"players":{"00-0033072":[{"statId":83,"yards":0,"clubcode":"CHI","sequence":2,"playerName":"L.Floyd"},{"statId":79,"yards":0,"clubcode":"CHI","sequence":3,"playerName":"L.Floyd"}],"00-0027974":[{"statId":20,"yards":0,"clubcode":"SF","sequence":1,"playerName":"C.Kaepernick"}]},"ydsnet":-4,"posteam":"SF","time":"05:50","ydstogo":7,"yrdln":"SF 28","note":null},"2677":{"sp":0,"desc":"C.Barth kicks 65 yards from CHI 35 to end zone, Touchback.","qtr":3,"down":0,"players":{"0":[{"statId":51,"yards":0,"clubcode":"SF","sequence":3,"playerName":""}],"00-0026138":[{"statId":410,"yards":66,"clubcode":"CHI","sequence":1,"playerName":"C.Barth"},{"statId":44,"yards":65,"clubcode":"CHI","sequence":2,"playerName":"C.Barth"}]},"ydsnet":0,"posteam":"CHI","time":"06:19","ydstogo":0,"yrdln":"CHI 35","note":"KICKOFF"},"2764":{"sp":0,"desc":"(5:08) (Shotgun) C.Kaepernick sacked at SF 21 for -7 yards (A.Hicks).","qtr":3,"down":3,"players":{"0":[{"statId":7,"yards":0,"clubcode":"SF","sequence":1,"playerName":""}],"00-0027974":[{"statId":20,"yards":-7,"clubcode":"SF","sequence":2,"playerName":"C.Kaepernick"}],"00-0029657":[{"statId":83,"yards":-7,"clubcode":"CHI","sequence":3,"playerName":"A.Hicks"},{"statId":110,"yards":0,"clubcode":"CHI","sequence":4,"playerName":"A.Hicks"},{"statId":79,"yards":0,"clubcode":"CHI","sequence":5,"playerName":"A.Hicks"},{"statId":120,"yards":0,"clubcode":"CHI","sequence":6,"playerName":"A.Hicks"},{"statId":402,"yards":7,"clubcode":"CHI","sequence":7,"playerName":"A.Hicks"}]},"ydsnet":-4,"posteam":"SF","time":"05:08","ydstogo":7,"yrdln":"SF 28","note":null},"2783":{"sp":0,"desc":"(4:29) (Punt formation) B.Pinion punts 44 yards to CHI 35, Center-K.Nelson, fair catch by B.Callahan.","qtr":3,"down":4,"players":{"00-0032065":[{"statId":29,"yards":44,"clubcode":"SF","sequence":1,"playerName":"B.Pinion"}],"00-0031904":[{"statId":39,"yards":0,"clubcode":"CHI","sequence":2,"playerName":"B.Callahan"}]},"ydsnet":-4,"posteam":"SF","time":"04:29","ydstogo":14,"yrdln":"SF 21","note":"PUNT"}},"redzone":true,"end":{"qtr":3,"time":"04:22","yrdln":"SF 21","team":"SF"},"start":{"qtr":3,"time":"06:19","yrdln":"SF 25","team":"SF"},"result":"Punt","penyds":-5,"postime":"1:57","posteam":"SF","numplays":6,"ydsgained":1},"22":{"qtr":4,"fds":1,"plays":{"3807":{"sp":0,"desc":"(4:00) (Shotgun) M.Barkley pass short right to D.Brown pushed ob at SF 43 for 6 yards (J.Tartt).","qtr":4,"down":3,"players":{"00-0030533":[{"statId":15,"yards":6,"clubcode":"CHI","sequence":3,"playerName":"M.Barkley"},{"statId":111,"yards":6,"clubcode":"CHI","sequence":4,"playerName":"M.Barkley"}],"00-0032057":[{"statId":79,"yards":0,"clubcode":"SF","sequence":8,"playerName":"J.Tartt"}],"0":[{"statId":4,"yards":0,"clubcode":"CHI","sequence":1,"playerName":""},{"statId":6,"yards":0,"clubcode":"CHI","sequence":2,"playerName":""}],"00-0032098":[{"statId":21,"yards":6,"clubcode":"CHI","sequence":5,"playerName":"D.Brown"},{"statId":115,"yards":0,"clubcode":"CHI","sequence":6,"playerName":"D.Brown"},{"statId":113,"yards":0,"clubcode":"CHI","sequence":7,"playerName":"D.Brown"}]},"ydsnet":11,"posteam":"CHI","time":"04:00","ydstogo":5,"yrdln":"SF 49","note":null},"3786":{"sp":0,"desc":"(4:47) J.Howard right tackle to SF 49 for 4 yards (G.Dorsey).","qtr":4,"down":2,"players":{"00-0032780":[{"statId":10,"yards":4,"clubcode":"CHI","sequence":1,"playerName":"J.Howard"}],"00-0026145":[{"statId":79,"yards":0,"clubcode":"SF","sequence":2,"playerName":"G.Dorsey"}]},"ydsnet":5,"posteam":"CHI","time":"04:47","ydstogo":9,"yrdln":"CHI 47","note":null},"3852":{"sp":0,"desc":"(3:14) J.Howard left tackle to SF 43 for 2 yards (A.Bethea).","qtr":4,"down":2,"players":{"00-0032780":[{"statId":10,"yards":2,"clubcode":"CHI","sequence":1,"playerName":"J.Howard"}],"00-0024421":[{"statId":79,"yards":0,"clubcode":"SF","sequence":2,"playerName":"A.Bethea"}]},"ydsnet":11,"posteam":"CHI","time":"03:14","ydstogo":12,"yrdln":"SF 45","note":null},"3911":{"sp":0,"desc":"(2:21) (Punt formation) P.O'Donnell punts 36 yards to SF 3, Center-P.Scales, downed by CHI-S.McManis.","qtr":4,"down":4,"players":{"0":[{"statId":38,"yards":0,"clubcode":"SF","sequence":3,"playerName":""}],"00-0031079":[{"statId":29,"yards":36,"clubcode":"CHI","sequence":1,"playerName":"P.O'Donnell"},{"statId":30,"yards":0,"clubcode":"CHI","sequence":2,"playerName":"P.O'Donnell"}]},"ydsnet":15,"posteam":"CHI","time":"02:21","ydstogo":6,"yrdln":"SF 39","note":"PUNT"},"3873":{"sp":0,"desc":"(2:27) J.Howard right tackle to SF 39 for 4 yards (D.Buckner).","qtr":4,"down":3,"players":{"00-0032780":[{"statId":10,"yards":4,"clubcode":"CHI","sequence":2,"playerName":"J.Howard"}],"0":[{"statId":7,"yards":0,"clubcode":"CHI","sequence":1,"playerName":""}],"00-0032378":[{"statId":79,"yards":0,"clubcode":"SF","sequence":3,"playerName":"D.Buckner"}]},"ydsnet":15,"posteam":"CHI","time":"02:27","ydstogo":10,"yrdln":"SF 43","note":null},"3894":{"sp":0,"desc":"Timeout #1 by SF at 02:21.","qtr":4,"down":0,"players":{"0":[{"statId":68,"yards":0,"clubcode":"SF","sequence":1,"playerName":""}]},"ydsnet":15,"posteam":"","time":"02:21","ydstogo":0,"yrdln":"","note":"TIMEOUT"},"3831":{"sp":0,"desc":"(3:55) J.Howard left tackle to SF 45 for -2 yards (G.Dorsey).","qtr":4,"down":1,"players":{"00-0032780":[{"statId":10,"yards":-2,"clubcode":"CHI","sequence":1,"playerName":"J.Howard"}],"0":[{"statId":95,"yards":-2,"clubcode":"CHI","sequence":2,"playerName":""}],"00-0026145":[{"statId":79,"yards":0,"clubcode":"SF","sequence":3,"playerName":"G.Dorsey"},{"statId":120,"yards":0,"clubcode":"SF","sequence":4,"playerName":"G.Dorsey"},{"statId":402,"yards":2,"clubcode":"SF","sequence":5,"playerName":"G.Dorsey"}]},"ydsnet":9,"posteam":"CHI","time":"03:55","ydstogo":10,"yrdln":"SF 43","note":null},"3765":{"sp":0,"desc":"(5:31) J.Howard left guard to CHI 47 for 1 yard (J.Ward).","qtr":4,"down":1,"players":{"00-0032780":[{"statId":10,"yards":1,"clubcode":"CHI","sequence":1,"playerName":"J.Howard"}],"00-0031298":[{"statId":79,"yards":0,"clubcode":"SF","sequence":2,"playerName":"J.Ward"}]},"ydsnet":5,"posteam":"CHI","time":"05:31","ydstogo":10,"yrdln":"CHI 46","note":null}},"redzone":true,"end":{"qtr":4,"time":"02:12","yrdln":"SF 39","team":"CHI"},"start":{"qtr":4,"time":"05:31","yrdln":"CHI 46","team":"CHI"},"result":"Punt","penyds":0,"postime":"3:19","posteam":"CHI","numplays":8,"ydsgained":15},"17":{"qtr":3,"fds":0,"plays":{"2977":{"sp":0,"desc":"(1:22) (Punt formation) B.Pinion punts 43 yards to CHI 36, Center-K.Nelson, fair catch by B.Callahan.","qtr":3,"down":4,"players":{"00-0032065":[{"statId":29,"yards":43,"clubcode":"SF","sequence":1,"playerName":"B.Pinion"}],"00-0031904":[{"statId":39,"yards":0,"clubcode":"CHI","sequence":2,"playerName":"B.Callahan"}]},"ydsnet":6,"posteam":"SF","time":"01:22","ydstogo":4,"yrdln":"SF 21","note":"PUNT"},"2928":{"sp":0,"desc":"(2:10) (No Huddle, Shotgun) C.Hyde left end to SF 21 for 6 yards (H.Jones-Quartey).","qtr":3,"down":2,"players":{"00-0031989":[{"statId":79,"yards":0,"clubcode":"CHI","sequence":2,"playerName":"H.Jones-Quartey"}],"00-0031045":[{"statId":10,"yards":6,"clubcode":"SF","sequence":1,"playerName":"C.Hyde"}]},"ydsnet":6,"posteam":"SF","time":"02:10","ydstogo":10,"yrdln":"SF 15","note":null},"2954":{"sp":0,"desc":"(1:27) (No Huddle, Shotgun) C.Kaepernick pass incomplete deep right to V.McDonald.","qtr":3,"down":3,"players":{"0":[{"statId":7,"yards":0,"clubcode":"SF","sequence":1,"playerName":""}],"00-0030470":[{"statId":115,"yards":0,"clubcode":"SF","sequence":3,"playerName":"V.McDonald"}],"00-0027974":[{"statId":14,"yards":0,"clubcode":"SF","sequence":2,"playerName":"C.Kaepernick"},{"statId":112,"yards":29,"clubcode":"SF","sequence":4,"playerName":"C.Kaepernick"}]},"ydsnet":6,"posteam":"SF","time":"01:27","ydstogo":4,"yrdln":"SF 21","note":null},"2904":{"sp":0,"desc":"(2:55) (Shotgun) C.Kaepernick sacked at SF 14 for -1 yards (A.Hicks). FUMBLES (A.Hicks) [A.Hicks], recovered by SF-J.Garnett at SF 15. J.Garnett to SF 15 for no gain (A.Hicks).","qtr":3,"down":1,"players":{"00-0029657":[{"statId":83,"yards":0,"clubcode":"CHI","sequence":2,"playerName":"A.Hicks"},{"statId":110,"yards":0,"clubcode":"CHI","sequence":3,"playerName":"A.Hicks"},{"statId":79,"yards":0,"clubcode":"CHI","sequence":4,"playerName":"A.Hicks"},{"statId":91,"yards":0,"clubcode":"CHI","sequence":6,"playerName":"A.Hicks"},{"statId":79,"yards":0,"clubcode":"CHI","sequence":8,"playerName":"A.Hicks"}],"00-0027974":[{"statId":20,"yards":0,"clubcode":"SF","sequence":1,"playerName":"C.Kaepernick"},{"statId":52,"yards":0,"clubcode":"SF","sequence":5,"playerName":"C.Kaepernick"}],"00-0033151":[{"statId":55,"yards":0,"clubcode":"SF","sequence":7,"playerName":"J.Garnett"}]},"ydsnet":6,"posteam":"SF","time":"02:55","ydstogo":10,"yrdln":"SF 15","note":"FUMBLE"}},"redzone":true,"end":{"qtr":3,"time":"01:14","yrdln":"SF 21","team":"SF"},"start":{"qtr":3,"time":"02:55","yrdln":"SF 15","team":"SF"},"result":"Punt","penyds":0,"postime":"1:41","posteam":"SF","numplays":4,"ydsgained":6},"23":{"qtr":4,"fds":0,"plays":{"3972":{"sp":1,"desc":"(2:00) (Shotgun) B.Gabbert sacked in End Zone for -8 yards, SAFETY (L.Floyd).","qtr":4,"down":2,"players":{"00-0033072":[{"statId":83,"yards":-8,"clubcode":"CHI","sequence":2,"playerName":"L.Floyd"},{"statId":110,"yards":0,"clubcode":"CHI","sequence":3,"playerName":"L.Floyd"},{"statId":89,"yards":0,"clubcode":"CHI","sequence":4,"playerName":"L.Floyd"},{"statId":79,"yards":0,"clubcode":"CHI","sequence":5,"playerName":"L.Floyd"},{"statId":120,"yards":0,"clubcode":"CHI","sequence":6,"playerName":"L.Floyd"},{"statId":402,"yards":8,"clubcode":"CHI","sequence":7,"playerName":"L.Floyd"}],"00-0027948":[{"statId":20,"yards":-8,"clubcode":"SF","sequence":1,"playerName":"B.Gabbert"}]},"ydsnet":-3,"posteam":"SF","time":"02:00","ydstogo":5,"yrdln":"SF 8","note":"SAF"},"3931":{"sp":0,"desc":"(2:12) (Shotgun) B.Gabbert pass short left to V.McDonald to SF 8 for 5 yards (C.LeBlanc).","qtr":4,"down":1,"players":{"00-0030470":[{"statId":21,"yards":5,"clubcode":"SF","sequence":3,"playerName":"V.McDonald"},{"statId":115,"yards":0,"clubcode":"SF","sequence":4,"playerName":"V.McDonald"},{"statId":113,"yards":0,"clubcode":"SF","sequence":5,"playerName":"V.McDonald"}],"00-0027948":[{"statId":15,"yards":5,"clubcode":"SF","sequence":1,"playerName":"B.Gabbert"},{"statId":111,"yards":5,"clubcode":"SF","sequence":2,"playerName":"B.Gabbert"}],"00-0032581":[{"statId":79,"yards":0,"clubcode":"CHI","sequence":6,"playerName":"C.LeBlanc"}]},"ydsnet":5,"posteam":"SF","time":"02:12","ydstogo":10,"yrdln":"SF 3","note":null},"3955":{"sp":0,"desc":"Two-Minute Warning","qtr":4,"down":0,"players":{},"ydsnet":5,"posteam":"","time":"02:00","ydstogo":0,"yrdln":"","note":null}},"redzone":true,"end":{"qtr":4,"time":"01:55","yrdln":"SF 8","team":"SF"},"start":{"qtr":4,"time":"02:12","yrdln":"SF 3","team":"SF"},"result":"Safety","penyds":0,"postime":"0:17","posteam":"SF","numplays":3,"ydsgained":-3},"14":{"qtr":3,"fds":3,"plays":{"2645":{"sp":1,"desc":"C.Barth extra point is GOOD, Center-P.Scales, Holder-P.O'Donnell.","qtr":3,"down":0,"players":{"00-0026138":[{"statId":72,"yards":0,"clubcode":"CHI","sequence":1,"playerName":"C.Barth"}]},"ydsnet":59,"posteam":"CHI","time":"06:19","ydstogo":0,"yrdln":"SF 15","note":"XP"},"2622":{"sp":1,"desc":"(6:25) J.Howard left guard for 5 yards, TOUCHDOWN.","qtr":3,"down":1,"players":{"00-0032780":[{"statId":11,"yards":5,"clubcode":"CHI","sequence":2,"playerName":"J.Howard"}],"0":[{"statId":3,"yards":0,"clubcode":"CHI","sequence":1,"playerName":""}]},"ydsnet":59,"posteam":"CHI","time":"06:25","ydstogo":5,"yrdln":"SF 5","note":"TD"},"2577":{"sp":0,"desc":"(7:52) J.Howard right guard to SF 36 for 1 yard (G.Hodges).","qtr":3,"down":1,"players":{"00-0032780":[{"statId":10,"yards":1,"clubcode":"CHI","sequence":1,"playerName":"J.Howard"}],"00-0030385":[{"statId":79,"yards":0,"clubcode":"SF","sequence":2,"playerName":"G.Hodges"}]},"ydsnet":23,"posteam":"CHI","time":"07:52","ydstogo":10,"yrdln":"SF 37","note":null},"2540":{"sp":0,"desc":"(8:32) M.Barkley pass deep left to J.Bellamy to SF 37 for 22 yards (T.Brock).","qtr":3,"down":1,"players":{"00-0030533":[{"statId":15,"yards":22,"clubcode":"CHI","sequence":2,"playerName":"M.Barkley"},{"statId":111,"yards":19,"clubcode":"CHI","sequence":3,"playerName":"M.Barkley"}],"0":[{"statId":4,"yards":0,"clubcode":"CHI","sequence":1,"playerName":""}],"00-0029319":[{"statId":21,"yards":22,"clubcode":"CHI","sequence":4,"playerName":"J.Bellamy"},{"statId":115,"yards":0,"clubcode":"CHI","sequence":5,"playerName":"J.Bellamy"},{"statId":113,"yards":3,"clubcode":"CHI","sequence":6,"playerName":"J.Bellamy"}],"00-0027375":[{"statId":79,"yards":0,"clubcode":"SF","sequence":7,"playerName":"T.Brock"}]},"ydsnet":22,"posteam":"CHI","time":"08:32","ydstogo":10,"yrdln":"CHI 41","note":null},"2598":{"sp":0,"desc":"(7:18) M.Barkley pass deep right to J.Bellamy to SF 5 for 31 yards (J.Ward).","qtr":3,"down":2,"players":{"00-0030533":[{"statId":15,"yards":31,"clubcode":"CHI","sequence":2,"playerName":"M.Barkley"},{"statId":111,"yards":31,"clubcode":"CHI","sequence":3,"playerName":"M.Barkley"}],"0":[{"statId":4,"yards":0,"clubcode":"CHI","sequence":1,"playerName":""}],"00-0029319":[{"statId":21,"yards":31,"clubcode":"CHI","sequence":4,"playerName":"J.Bellamy"},{"statId":115,"yards":0,"clubcode":"CHI","sequence":5,"playerName":"J.Bellamy"},{"statId":113,"yards":0,"clubcode":"CHI","sequence":6,"playerName":"J.Bellamy"}],"00-0031298":[{"statId":79,"yards":0,"clubcode":"SF","sequence":7,"playerName":"J.Ward"}]},"ydsnet":54,"posteam":"CHI","time":"07:18","ydstogo":9,"yrdln":"SF 36","note":null}},"redzone":true,"end":{"qtr":3,"time":"06:19","yrdln":"SF 5","team":"CHI"},"start":{"qtr":3,"time":"08:32","yrdln":"CHI 41","team":"CHI"},"result":"Touchdown","penyds":0,"postime":"2:13","posteam":"CHI","numplays":5,"ydsgained":59},"crntdrv":24,"11":{"qtr":2,"fds":0,"plays":{"2054":{"sp":0,"desc":"(:31) C.Kaepernick kneels to SF 24 for -1 yards.","qtr":2,"down":1,"players":{"00-0027974":[{"statId":10,"yards":-1,"clubcode":"SF","sequence":1,"playerName":"C.Kaepernick"}]},"ydsnet":-1,"posteam":"SF","time":"00:31","ydstogo":10,"yrdln":"SF 25","note":null},"2075":{"sp":0,"desc":"END QUARTER 2","qtr":2,"down":0,"players":{},"ydsnet":-1,"posteam":"","time":"","ydstogo":0,"yrdln":"","note":null},"2039":{"sp":0,"desc":"C.Barth kicks 65 yards from CHI 35 to end zone, Touchback.","qtr":2,"down":0,"players":{"0":[{"statId":51,"yards":0,"clubcode":"SF","sequence":3,"playerName":""}],"00-0026138":[{"statId":410,"yards":75,"clubcode":"CHI","sequence":1,"playerName":"C.Barth"},{"statId":44,"yards":65,"clubcode":"CHI","sequence":2,"playerName":"C.Barth"}]},"ydsnet":0,"posteam":"CHI","time":"00:31","ydstogo":0,"yrdln":"CHI 35","note":"KICKOFF"}},"redzone":true,"end":{"qtr":2,"time":"00:00","yrdln":"SF 25","team":"SF"},"start":{"qtr":2,"time":"00:31","yrdln":"SF 25","team":"SF"},"result":"End of Half","penyds":0,"postime":"0:31","posteam":"SF","numplays":3,"ydsgained":-1},"24":{"qtr":4,"fds":0,"plays":{"4074":{"sp":0,"desc":"(:39) M.Barkley kneels to CHI 32 for -1 yards.","qtr":4,"down":3,"players":{"00-0030533":[{"statId":10,"yards":-1,"clubcode":"CHI","sequence":2,"playerName":"M.Barkley"}],"0":[{"statId":7,"yards":0,"clubcode":"CHI","sequence":1,"playerName":""}]},"ydsnet":-1,"posteam":"CHI","time":"00:39","ydstogo":10,"yrdln":"CHI 33","note":null},"4032":{"sp":0,"desc":"(1:54) J.Howard left guard to CHI 34 for 1 yard (N.Bellore).","qtr":4,"down":1,"players":{"00-0028292":[{"statId":79,"yards":0,"clubcode":"SF","sequence":2,"playerName":"N.Bellore"}],"00-0032780":[{"statId":10,"yards":1,"clubcode":"CHI","sequence":1,"playerName":"J.Howard"}]},"ydsnet":1,"posteam":"CHI","time":"01:54","ydstogo":10,"yrdln":"CHI 33","note":null},"4095":{"sp":0,"desc":"END GAME","qtr":4,"down":0,"players":{},"ydsnet":-1,"posteam":"","time":"","ydstogo":0,"yrdln":"","note":null},"4053":{"sp":0,"desc":"(1:08) M.Barkley kneels to CHI 33 for -1 yards.","qtr":4,"down":2,"players":{"00-0030533":[{"statId":10,"yards":-1,"clubcode":"CHI","sequence":1,"playerName":"M.Barkley"}]},"ydsnet":0,"posteam":"CHI","time":"01:08","ydstogo":9,"yrdln":"CHI 34","note":null},"4010":{"sp":0,"desc":"B.Pinion kicks 47 yards from SF 20 to CHI 33. B.Callahan (didn't try to advance) to CHI 33 for no gain (M.Ball).","qtr":4,"down":0,"players":{"00-0030640":[{"statId":79,"yards":0,"clubcode":"SF","sequence":3,"playerName":"M.Ball"}],"00-0032065":[{"statId":41,"yards":47,"clubcode":"SF","sequence":1,"playerName":"B.Pinion"}],"00-0031904":[{"statId":45,"yards":0,"clubcode":"CHI","sequence":2,"playerName":"B.Callahan"}]},"ydsnet":0,"posteam":"SF","time":"01:55","ydstogo":0,"yrdln":"SF 20","note":"KICKOFF"}},"redzone":true,"end":{"qtr":4,"time":"00:00","yrdln":"","team":"CHI"},"start":{"qtr":4,"time":"01:55","yrdln":"CHI 33","team":"CHI"},"result":"End of Game","penyds":0,"postime":"1:55","posteam":"CHI","numplays":5,"ydsgained":-1},"4":{"qtr":1,"fds":0,"plays":{"589":{"sp":0,"desc":"(6:05) (Shotgun) M.Barkley pass incomplete deep left to M.Wilson.","qtr":1,"down":3,"players":{"00-0030533":[{"statId":14,"yards":0,"clubcode":"CHI","sequence":2,"playerName":"M.Barkley"},{"statId":112,"yards":22,"clubcode":"CHI","sequence":4,"playerName":"M.Barkley"}],"0":[{"statId":7,"yards":0,"clubcode":"CHI","sequence":1,"playerName":""}],"00-0030047":[{"statId":115,"yards":0,"clubcode":"CHI","sequence":3,"playerName":"M.Wilson"}]},"ydsnet":-4,"posteam":"CHI","time":"06:05","ydstogo":14,"yrdln":"CHI 38","note":null},"547":{"sp":0,"desc":"(7:22) J.Howard left end to CHI 35 for -2 yards (E.Harold).","qtr":1,"down":1,"players":{"00-0032060":[{"statId":79,"yards":0,"clubcode":"SF","sequence":3,"playerName":"E.Harold"},{"statId":120,"yards":0,"clubcode":"SF","sequence":4,"playerName":"E.Harold"},{"statId":402,"yards":2,"clubcode":"SF","sequence":5,"playerName":"E.Harold"}],"00-0032780":[{"statId":10,"yards":-2,"clubcode":"CHI","sequence":1,"playerName":"J.Howard"}],"0":[{"statId":95,"yards":-2,"clubcode":"CHI","sequence":2,"playerName":""}]},"ydsnet":-7,"posteam":"CHI","time":"07:22","ydstogo":15,"yrdln":"CHI 37","note":null},"524":{"sp":0,"desc":"(7:22) PENALTY on CHI-E.Kush, False Start, 5 yards, enforced at CHI 42 - No Play.","qtr":1,"down":1,"players":{"00-0030094":[{"statId":93,"yards":5,"clubcode":"CHI","sequence":1,"playerName":"E.Kush"}]},"ydsnet":-5,"posteam":"CHI","time":"07:22","ydstogo":10,"yrdln":"CHI 42","note":"PENALTY"},"568":{"sp":0,"desc":"(6:42) (Shotgun) J.Howard left guard to CHI 38 for 3 yards (G.Dorsey; D.Buckner).","qtr":1,"down":2,"players":{"00-0032780":[{"statId":10,"yards":3,"clubcode":"CHI","sequence":1,"playerName":"J.Howard"}],"00-0032378":[{"statId":82,"yards":0,"clubcode":"SF","sequence":3,"playerName":"D.Buckner"}],"00-0026145":[{"statId":82,"yards":0,"clubcode":"SF","sequence":2,"playerName":"G.Dorsey"}]},"ydsnet":-4,"posteam":"CHI","time":"06:42","ydstogo":17,"yrdln":"CHI 35","note":null},"611":{"sp":0,"desc":"(6:00) (Punt formation) P.O'Donnell punts 40 yards to SF 22, Center-P.Scales, fair catch by J.Kerley. PENALTY on SF-S.Draughn, Offensive Holding, 10 yards, enforced at SF 22.","qtr":1,"down":4,"players":{"00-0028202":[{"statId":93,"yards":10,"clubcode":"SF","sequence":3,"playerName":"S.Draughn"}],"00-0028091":[{"statId":39,"yards":0,"clubcode":"SF","sequence":2,"playerName":"J.Kerley"}],"00-0031079":[{"statId":29,"yards":40,"clubcode":"CHI","sequence":1,"playerName":"P.O'Donnell"}]},"ydsnet":-4,"posteam":"CHI","time":"06:00","ydstogo":14,"yrdln":"CHI 38","note":"PUNT"}},"redzone":true,"end":{"qtr":1,"time":"05:52","yrdln":"CHI 38","team":"CHI"},"start":{"qtr":1,"time":"07:22","yrdln":"CHI 42","team":"CHI"},"result":"Punt","penyds":-5,"postime":"1:30","posteam":"CHI","numplays":5,"ydsgained":1},"9":{"qtr":2,"fds":2,"plays":{"1590":{"sp":0,"desc":"(4:52) (No Huddle, Shotgun) D.Harris left end to CHI 11 for 9 yards (H.Jones-Quartey).","qtr":2,"down":2,"players":{"0":[{"statId":3,"yards":0,"clubcode":"SF","sequence":1,"playerName":""}],"00-0031989":[{"statId":79,"yards":0,"clubcode":"CHI","sequence":3,"playerName":"H.Jones-Quartey"}],"00-0028409":[{"statId":10,"yards":9,"clubcode":"SF","sequence":2,"playerName":"D.Harris"}]},"ydsnet":26,"posteam":"SF","time":"04:52","ydstogo":7,"yrdln":"CHI 20","note":null},"1548":{"sp":0,"desc":"(6:01) (No Huddle, Shotgun) C.Hyde left tackle to CHI 23 for 6 yards (C.LeBlanc).","qtr":2,"down":3,"players":{"0":[{"statId":3,"yards":0,"clubcode":"SF","sequence":1,"playerName":""},{"statId":6,"yards":0,"clubcode":"SF","sequence":2,"playerName":""}],"00-0032581":[{"statId":79,"yards":0,"clubcode":"CHI","sequence":4,"playerName":"C.LeBlanc"}],"00-0031045":[{"statId":10,"yards":6,"clubcode":"SF","sequence":3,"playerName":"C.Hyde"}]},"ydsnet":14,"posteam":"SF","time":"06:01","ydstogo":2,"yrdln":"CHI 29","note":null},"1691":{"sp":1,"desc":"(2:00) (Field Goal formation) P.Dawson 28 yard field goal is GOOD, Center-K.Nelson, Holder-B.Pinion.","qtr":2,"down":4,"players":{"00-0004091":[{"statId":70,"yards":28,"clubcode":"SF","sequence":1,"playerName":"P.Dawson"}]},"ydsnet":27,"posteam":"SF","time":"02:00","ydstogo":9,"yrdln":"CHI 10","note":"FG"},"1653":{"sp":0,"desc":"(2:45) (No Huddle, Shotgun) C.Hyde left guard to CHI 10 for 5 yards (H.Jones-Quartey; J.Timu).","qtr":2,"down":3,"players":{"0":[{"statId":7,"yards":0,"clubcode":"SF","sequence":1,"playerName":""}],"00-0031989":[{"statId":82,"yards":0,"clubcode":"CHI","sequence":3,"playerName":"H.Jones-Quartey"}],"00-0031915":[{"statId":82,"yards":0,"clubcode":"CHI","sequence":4,"playerName":"J.Timu"}],"00-0031045":[{"statId":10,"yards":5,"clubcode":"SF","sequence":2,"playerName":"C.Hyde"}]},"ydsnet":27,"posteam":"SF","time":"02:45","ydstogo":14,"yrdln":"CHI 15","note":null},"1632":{"sp":0,"desc":"(3:26) (No Huddle, Shotgun) C.Kaepernick right end to CHI 15 for -3 yards (H.Jones-Quartey).","qtr":2,"down":2,"players":{"0":[{"statId":95,"yards":-3,"clubcode":"SF","sequence":2,"playerName":""}],"00-0027974":[{"statId":10,"yards":-3,"clubcode":"SF","sequence":1,"playerName":"C.Kaepernick"}],"00-0031989":[{"statId":79,"yards":0,"clubcode":"CHI","sequence":3,"playerName":"H.Jones-Quartey"},{"statId":120,"yards":0,"clubcode":"CHI","sequence":4,"playerName":"H.Jones-Quartey"},{"statId":402,"yards":3,"clubcode":"CHI","sequence":5,"playerName":"H.Jones-Quartey"}]},"ydsnet":22,"posteam":"SF","time":"03:26","ydstogo":11,"yrdln":"CHI 12","note":null},"1611":{"sp":0,"desc":"(4:11) (No Huddle, Shotgun) D.Harris left guard to CHI 12 for -1 yards (N.Kwiatkoski).","qtr":2,"down":1,"players":{"0":[{"statId":95,"yards":-1,"clubcode":"SF","sequence":2,"playerName":""}],"00-0032773":[{"statId":79,"yards":0,"clubcode":"CHI","sequence":3,"playerName":"N.Kwiatkoski"},{"statId":120,"yards":0,"clubcode":"CHI","sequence":4,"playerName":"N.Kwiatkoski"},{"statId":402,"yards":1,"clubcode":"CHI","sequence":5,"playerName":"N.Kwiatkoski"}],"00-0028409":[{"statId":10,"yards":-1,"clubcode":"SF","sequence":1,"playerName":"D.Harris"}]},"ydsnet":25,"posteam":"SF","time":"04:11","ydstogo":10,"yrdln":"CHI 11","note":null},"1505":{"sp":0,"desc":"(6:47) (Shotgun) C.Hyde left guard to CHI 31 for 6 yards (N.Kwiatkoski).","qtr":2,"down":1,"players":{"00-0032773":[{"statId":79,"yards":0,"clubcode":"CHI","sequence":2,"playerName":"N.Kwiatkoski"}],"00-0031045":[{"statId":10,"yards":6,"clubcode":"SF","sequence":1,"playerName":"C.Hyde"}]},"ydsnet":6,"posteam":"SF","time":"06:47","ydstogo":10,"yrdln":"CHI 37","note":null},"1526":{"sp":0,"desc":"(6:11) (No Huddle, Shotgun) C.Kaepernick left end pushed ob at CHI 29 for 2 yards (H.Jones-Quartey).","qtr":2,"down":2,"players":{"00-0027974":[{"statId":10,"yards":2,"clubcode":"SF","sequence":1,"playerName":"C.Kaepernick"}],"00-0031989":[{"statId":79,"yards":0,"clubcode":"CHI","sequence":2,"playerName":"H.Jones-Quartey"}]},"ydsnet":8,"posteam":"SF","time":"06:11","ydstogo":4,"yrdln":"CHI 31","note":null},"1569":{"sp":0,"desc":"(5:25) (No Huddle, Shotgun) S.Draughn right tackle to CHI 20 for 3 yards (N.Kwiatkoski).","qtr":2,"down":1,"players":{"00-0028202":[{"statId":10,"yards":3,"clubcode":"SF","sequence":1,"playerName":"S.Draughn"}],"00-0032773":[{"statId":79,"yards":0,"clubcode":"CHI","sequence":2,"playerName":"N.Kwiatkoski"}]},"ydsnet":17,"posteam":"SF","time":"05:25","ydstogo":10,"yrdln":"CHI 23","note":null},"1674":{"sp":0,"desc":"Two-Minute Warning","qtr":2,"down":0,"players":{},"ydsnet":27,"posteam":"","time":"02:00","ydstogo":0,"yrdln":"","note":null}},"redzone":true,"end":{"qtr":2,"time":"01:56","yrdln":"CHI 10","team":"SF"},"start":{"qtr":2,"time":"06:47","yrdln":"CHI 37","team":"SF"},"result":"Field Goal","penyds":0,"postime":"4:51","posteam":"SF","numplays":10,"ydsgained":27},"7":{"qtr":2,"fds":0,"plays":{"1327":{"sp":0,"desc":"(8:23) (No Huddle, Shotgun) C.Hyde left guard to CHI 17 for 3 yards (A.Hicks).","qtr":2,"down":2,"players":{"00-0029657":[{"statId":79,"yards":0,"clubcode":"CHI","sequence":2,"playerName":"A.Hicks"}],"00-0031045":[{"statId":10,"yards":3,"clubcode":"SF","sequence":1,"playerName":"C.Hyde"}]},"ydsnet":2,"posteam":"SF","time":"08:23","ydstogo":11,"yrdln":"CHI 20","note":null},"1306":{"sp":0,"desc":"(9:07) (Shotgun) C.Hyde left tackle to CHI 20 for -1 yards (N.Kwiatkoski).","qtr":2,"down":1,"players":{"0":[{"statId":95,"yards":-1,"clubcode":"SF","sequence":2,"playerName":""}],"00-0032773":[{"statId":79,"yards":0,"clubcode":"CHI","sequence":3,"playerName":"N.Kwiatkoski"},{"statId":120,"yards":0,"clubcode":"CHI","sequence":4,"playerName":"N.Kwiatkoski"},{"statId":402,"yards":1,"clubcode":"CHI","sequence":5,"playerName":"N.Kwiatkoski"}],"00-0031045":[{"statId":10,"yards":-1,"clubcode":"SF","sequence":1,"playerName":"C.Hyde"}]},"ydsnet":-1,"posteam":"SF","time":"09:07","ydstogo":10,"yrdln":"CHI 19","note":null},"1372":{"sp":1,"desc":"(6:59) (Field Goal formation) P.Dawson 31 yard field goal is GOOD, Center-K.Nelson, Holder-B.Pinion.","qtr":2,"down":4,"players":{"00-0004091":[{"statId":70,"yards":31,"clubcode":"SF","sequence":1,"playerName":"P.Dawson"}]},"ydsnet":6,"posteam":"SF","time":"06:59","ydstogo":4,"yrdln":"CHI 13","note":"FG"},"1348":{"sp":0,"desc":"(7:41) (No Huddle, Shotgun) C.Kaepernick pass short right to V.McDonald to CHI 13 for 4 yards (H.Jones-Quartey).","qtr":2,"down":3,"players":{"0":[{"statId":7,"yards":0,"clubcode":"SF","sequence":1,"playerName":""}],"00-0030470":[{"statId":21,"yards":4,"clubcode":"SF","sequence":4,"playerName":"V.McDonald"},{"statId":115,"yards":0,"clubcode":"SF","sequence":5,"playerName":"V.McDonald"},{"statId":113,"yards":2,"clubcode":"SF","sequence":6,"playerName":"V.McDonald"}],"00-0027974":[{"statId":15,"yards":4,"clubcode":"SF","sequence":2,"playerName":"C.Kaepernick"},{"statId":111,"yards":2,"clubcode":"SF","sequence":3,"playerName":"C.Kaepernick"}],"00-0031989":[{"statId":79,"yards":0,"clubcode":"CHI","sequence":7,"playerName":"H.Jones-Quartey"}]},"ydsnet":6,"posteam":"SF","time":"07:41","ydstogo":8,"yrdln":"CHI 17","note":null}},"redzone":true,"end":{"qtr":2,"time":"06:55","yrdln":"CHI 13","team":"SF"},"start":{"qtr":2,"time":"09:07","yrdln":"CHI 19","team":"SF"},"result":"Field Goal","penyds":0,"postime":"2:12","posteam":"SF","numplays":4,"ydsgained":6},"13":{"qtr":3,"fds":0,"plays":{"2438":{"sp":0,"desc":"(9:26) (Shotgun) C.Hyde right guard to SF 24 for 4 yards (A.Hicks; M.Unrein).","qtr":3,"down":1,"players":{"00-0029657":[{"statId":82,"yards":0,"clubcode":"CHI","sequence":2,"playerName":"A.Hicks"}],"00-0027573":[{"statId":82,"yards":0,"clubcode":"CHI","sequence":3,"playerName":"M.Unrein"}],"00-0031045":[{"statId":10,"yards":4,"clubcode":"SF","sequence":1,"playerName":"C.Hyde"}]},"ydsnet":4,"posteam":"SF","time":"09:26","ydstogo":10,"yrdln":"SF 20","note":null},"2481":{"sp":0,"desc":"(8:46) (Shotgun) C.Kaepernick pass incomplete deep left to S.Draughn (J.Timu).","qtr":3,"down":3,"players":{"0":[{"statId":7,"yards":0,"clubcode":"SF","sequence":1,"playerName":""}],"00-0028202":[{"statId":115,"yards":0,"clubcode":"SF","sequence":3,"playerName":"S.Draughn"}],"00-0027974":[{"statId":14,"yards":0,"clubcode":"SF","sequence":2,"playerName":"C.Kaepernick"},{"statId":112,"yards":31,"clubcode":"SF","sequence":5,"playerName":"C.Kaepernick"}],"00-0031915":[{"statId":85,"yards":0,"clubcode":"CHI","sequence":4,"playerName":"J.Timu"}]},"ydsnet":4,"posteam":"SF","time":"08:46","ydstogo":6,"yrdln":"SF 24","note":null},"2503":{"sp":0,"desc":"(8:39) (Punt formation) B.Pinion punts 40 yards to CHI 36, Center-K.Nelson, fair catch by B.Callahan. PENALTY on SF-A.Burbridge, Illegal Shift, 5 yards, enforced at CHI 36.","qtr":3,"down":4,"players":{"00-0032065":[{"statId":29,"yards":40,"clubcode":"SF","sequence":1,"playerName":"B.Pinion"}],"00-0032441":[{"statId":93,"yards":5,"clubcode":"SF","sequence":3,"playerName":"A.Burbridge"}],"00-0031904":[{"statId":39,"yards":0,"clubcode":"CHI","sequence":2,"playerName":"B.Callahan"}]},"ydsnet":4,"posteam":"SF","time":"08:39","ydstogo":6,"yrdln":"SF 24","note":"PUNT"},"2459":{"sp":0,"desc":"(8:51) (No Huddle, Shotgun) C.Kaepernick pass incomplete short left to J.Kerley.","qtr":3,"down":2,"players":{"00-0027974":[{"statId":14,"yards":0,"clubcode":"SF","sequence":1,"playerName":"C.Kaepernick"},{"statId":112,"yards":8,"clubcode":"SF","sequence":3,"playerName":"C.Kaepernick"}],"00-0028091":[{"statId":115,"yards":0,"clubcode":"SF","sequence":2,"playerName":"J.Kerley"}]},"ydsnet":4,"posteam":"SF","time":"08:51","ydstogo":6,"yrdln":"SF 24","note":null},"2396":{"sp":0,"desc":"C.Barth kicks 62 yards from CHI 35 to SF 3. J.Shepherd to SF 20 for 17 yards (B.Braunecker). CHI-C.Jones was injured during the play.","qtr":3,"down":0,"players":{"00-0032661":[{"statId":79,"yards":0,"clubcode":"CHI","sequence":3,"playerName":"B.Braunecker"}],"00-0032137":[{"statId":45,"yards":17,"clubcode":"SF","sequence":2,"playerName":"J.Shepherd"}],"00-0026138":[{"statId":41,"yards":62,"clubcode":"CHI","sequence":1,"playerName":"C.Barth"}]},"ydsnet":0,"posteam":"CHI","time":"09:32","ydstogo":0,"yrdln":"CHI 35","note":"KICKOFF"},"2421":{"sp":0,"desc":"Timeout at 09:26.","qtr":3,"down":0,"players":{},"ydsnet":0,"posteam":"","time":"09:26","ydstogo":0,"yrdln":"","note":"Timeout"}},"redzone":true,"end":{"qtr":3,"time":"08:32","yrdln":"SF 24","team":"SF"},"start":{"qtr":3,"time":"09:32","yrdln":"SF 20","team":"SF"},"result":"Punt","penyds":0,"postime":"1:00","posteam":"SF","numplays":6,"ydsgained":4},"1":{"qtr":1,"fds":2,"plays":{"133":{"sp":0,"desc":"(13:39) (No Huddle, Shotgun) C.Kaepernick pass incomplete short middle to R.Streater.","qtr":1,"down":1,"players":{"00-0027974":[{"statId":14,"yards":0,"clubcode":"SF","sequence":1,"playerName":"C.Kaepernick"},{"statId":112,"yards":9,"clubcode":"SF","sequence":3,"playerName":"C.Kaepernick"}],"00-0029129":[{"statId":115,"yards":0,"clubcode":"SF","sequence":2,"playerName":"R.Streater"}]},"ydsnet":27,"posteam":"SF","time":"13:39","ydstogo":10,"yrdln":"CHI 44","note":null},"36":{"sp":0,"desc":"C.Barth kicks 60 yards from CHI 35 to SF 5. J.Shepherd pushed ob at SF 29 for 24 yards (C.Prosinski).","qtr":1,"down":0,"players":{"00-0028059":[{"statId":79,"yards":0,"clubcode":"CHI","sequence":3,"playerName":"C.Prosinski"}],"00-0032137":[{"statId":45,"yards":24,"clubcode":"SF","sequence":2,"playerName":"J.Shepherd"}],"00-0026138":[{"statId":41,"yards":60,"clubcode":"CHI","sequence":1,"playerName":"C.Barth"}]},"ydsnet":0,"posteam":"CHI","time":"15:00","ydstogo":0,"yrdln":"CHI 35","note":"KICKOFF"},"112":{"sp":0,"desc":"(14:12) (Shotgun) C.Hyde right tackle to CHI 44 for 5 yards (E.Goldman).","qtr":1,"down":2,"players":{"00-0031045":[{"statId":10,"yards":5,"clubcode":"SF","sequence":2,"playerName":"C.Hyde"}],"0":[{"statId":3,"yards":0,"clubcode":"SF","sequence":1,"playerName":""}],"00-0031551":[{"statId":79,"yards":0,"clubcode":"CHI","sequence":3,"playerName":"E.Goldman"}]},"ydsnet":27,"posteam":"SF","time":"14:12","ydstogo":3,"yrdln":"CHI 49","note":null},"155":{"sp":0,"desc":"(13:36) (Shotgun) S.Draughn right guard to CHI 15 for 29 yards (D.Bush). PENALTY on SF-V.McDonald, Offensive Holding, 10 yards, enforced at CHI 35.","qtr":1,"down":2,"players":{"00-0030470":[{"statId":93,"yards":10,"clubcode":"SF","sequence":3,"playerName":"V.McDonald"}],"00-0032774":[{"statId":79,"yards":0,"clubcode":"CHI","sequence":2,"playerName":"D.Bush"}],"00-0028202":[{"statId":10,"yards":9,"clubcode":"SF","sequence":1,"playerName":"S.Draughn"}]},"ydsnet":13,"posteam":"SF","time":"13:36","ydstogo":10,"yrdln":"CHI 44","note":"PENALTY"},"58":{"sp":0,"desc":"(14:50) (Shotgun) C.Kaepernick pass incomplete short right to T.Smith (T.Porter). PENALTY on CHI-A.Hicks, Roughing the Passer, 15 yards, enforced at SF 29 - No Play.","qtr":1,"down":1,"players":{"00-0029657":[{"statId":93,"yards":15,"clubcode":"CHI","sequence":2,"playerName":"A.Hicks"}],"0":[{"statId":5,"yards":0,"clubcode":"SF","sequence":1,"playerName":""}]},"ydsnet":15,"posteam":"SF","time":"14:50","ydstogo":10,"yrdln":"SF 29","note":"PENALTY"},"227":{"sp":0,"desc":"(11:58) (Punt formation) B.Pinion punts 39 yards to CHI 19, Center-K.Nelson, fair catch by B.Callahan. PENALTY on SF, Fair Catch Interference, 15 yards, enforced at CHI 19.","qtr":1,"down":4,"players":{"00-0031904":[{"statId":39,"yards":0,"clubcode":"CHI","sequence":3,"playerName":"B.Callahan"}],"00-0032065":[{"statId":29,"yards":39,"clubcode":"SF","sequence":1,"playerName":"B.Pinion"},{"statId":30,"yards":0,"clubcode":"SF","sequence":2,"playerName":"B.Pinion"}],"0":[{"statId":93,"yards":15,"clubcode":"SF","sequence":4,"playerName":""}]},"ydsnet":13,"posteam":"SF","time":"11:58","ydstogo":24,"yrdln":"SF 42","note":"PUNT"},"91":{"sp":0,"desc":"(14:46) (Shotgun) C.Hyde left guard to CHI 49 for 7 yards (C.LeBlanc).","qtr":1,"down":1,"players":{"00-0032581":[{"statId":79,"yards":0,"clubcode":"CHI","sequence":2,"playerName":"C.LeBlanc"}],"00-0031045":[{"statId":10,"yards":7,"clubcode":"SF","sequence":1,"playerName":"C.Hyde"}]},"ydsnet":22,"posteam":"SF","time":"14:46","ydstogo":10,"yrdln":"SF 44","note":null},"206":{"sp":0,"desc":"(12:28) (Shotgun) C.Hyde right guard to SF 42 for no gain (A.Hicks).","qtr":1,"down":3,"players":{"00-0029657":[{"statId":79,"yards":0,"clubcode":"CHI","sequence":3,"playerName":"A.Hicks"}],"0":[{"statId":7,"yards":0,"clubcode":"SF","sequence":1,"playerName":""}],"00-0031045":[{"statId":10,"yards":0,"clubcode":"SF","sequence":2,"playerName":"C.Hyde"}]},"ydsnet":13,"posteam":"SF","time":"12:28","ydstogo":24,"yrdln":"SF 42","note":null},"187":{"sp":0,"desc":"(13:00) (Shotgun) C.Kaepernick sacked at SF 42 for -13 yards (W.Young).","qtr":1,"down":2,"players":{"00-0027974":[{"statId":20,"yards":-13,"clubcode":"SF","sequence":1,"playerName":"C.Kaepernick"}],"00-0027808":[{"statId":83,"yards":-13,"clubcode":"CHI","sequence":2,"playerName":"W.Young"},{"statId":110,"yards":0,"clubcode":"CHI","sequence":3,"playerName":"W.Young"},{"statId":79,"yards":0,"clubcode":"CHI","sequence":4,"playerName":"W.Young"},{"statId":120,"yards":0,"clubcode":"CHI","sequence":5,"playerName":"W.Young"},{"statId":402,"yards":13,"clubcode":"CHI","sequence":6,"playerName":"W.Young"}]},"ydsnet":13,"posteam":"SF","time":"13:00","ydstogo":11,"yrdln":"CHI 45","note":null}},"redzone":true,"end":{"qtr":1,"time":"11:51","yrdln":"SF 42","team":"SF"},"start":{"qtr":1,"time":"15:00","yrdln":"SF 29","team":"SF"},"result":"Punt","penyds":5,"postime":"3:09","posteam":"SF","numplays":9,"ydsgained":8},"12":{"qtr":3,"fds":4,"plays":{"2151":{"sp":0,"desc":"(14:16) J.Howard left guard to CHI 40 for 4 yards (D.Buckner).","qtr":3,"down":1,"players":{"00-0032780":[{"statId":10,"yards":4,"clubcode":"CHI","sequence":1,"playerName":"J.Howard"}],"00-0032378":[{"statId":79,"yards":0,"clubcode":"SF","sequence":2,"playerName":"D.Buckner"}]},"ydsnet":15,"posteam":"CHI","time":"14:16","ydstogo":10,"yrdln":"CHI 36","note":null},"2184":{"sp":0,"desc":"(13:39) J.Howard right tackle to CHI 40 for no gain (D.Buckner).","qtr":3,"down":2,"players":{"00-0032780":[{"statId":10,"yards":0,"clubcode":"CHI","sequence":1,"playerName":"J.Howard"}],"00-0032378":[{"statId":79,"yards":0,"clubcode":"SF","sequence":2,"playerName":"D.Buckner"}]},"ydsnet":15,"posteam":"CHI","time":"13:39","ydstogo":6,"yrdln":"CHI 40","note":null},"2230":{"sp":0,"desc":"(12:20) (Shotgun) M.Barkley pass incomplete short left to J.Howard [D.Buckner].","qtr":3,"down":1,"players":{"00-0030533":[{"statId":14,"yards":0,"clubcode":"CHI","sequence":1,"playerName":"M.Barkley"},{"statId":112,"yards":3,"clubcode":"CHI","sequence":4,"playerName":"M.Barkley"}],"00-0032780":[{"statId":115,"yards":0,"clubcode":"CHI","sequence":2,"playerName":"J.Howard"}],"00-0032378":[{"statId":110,"yards":0,"clubcode":"SF","sequence":3,"playerName":"D.Buckner"}]},"ydsnet":37,"posteam":"CHI","time":"12:20","ydstogo":10,"yrdln":"SF 38","note":null},"2342":{"sp":1,"desc":"(9:36) J.Howard left tackle for 2 yards, TOUCHDOWN.","qtr":3,"down":3,"players":{"00-0032780":[{"statId":11,"yards":2,"clubcode":"CHI","sequence":3,"playerName":"J.Howard"}],"0":[{"statId":3,"yards":0,"clubcode":"CHI","sequence":1,"playerName":""},{"statId":6,"yards":0,"clubcode":"CHI","sequence":2,"playerName":""}]},"ydsnet":75,"posteam":"CHI","time":"09:36","ydstogo":1,"yrdln":"SF 2","note":"TD"},"2092":{"sp":0,"desc":"P.Dawson kicks 65 yards from SF 35 to end zone, Touchback.","qtr":3,"down":0,"players":{"00-0004091":[{"statId":410,"yards":69,"clubcode":"SF","sequence":1,"playerName":"P.Dawson"},{"statId":44,"yards":65,"clubcode":"SF","sequence":2,"playerName":"P.Dawson"}],"0":[{"statId":51,"yards":0,"clubcode":"CHI","sequence":3,"playerName":""}]},"ydsnet":0,"posteam":"SF","time":"15:00","ydstogo":0,"yrdln":"SF 35","note":"KICKOFF"},"2318":{"sp":0,"desc":"(10:14) (Shotgun) M.Barkley pass short middle to D.Brown to SF 2 for 7 yards (A.Bethea).","qtr":3,"down":2,"players":{"00-0030533":[{"statId":15,"yards":7,"clubcode":"CHI","sequence":1,"playerName":"M.Barkley"},{"statId":111,"yards":-2,"clubcode":"CHI","sequence":2,"playerName":"M.Barkley"}],"00-0024421":[{"statId":79,"yards":0,"clubcode":"SF","sequence":6,"playerName":"A.Bethea"}],"00-0032098":[{"statId":21,"yards":7,"clubcode":"CHI","sequence":3,"playerName":"D.Brown"},{"statId":115,"yards":0,"clubcode":"CHI","sequence":4,"playerName":"D.Brown"},{"statId":113,"yards":9,"clubcode":"CHI","sequence":5,"playerName":"D.Brown"}]},"ydsnet":75,"posteam":"CHI","time":"10:14","ydstogo":8,"yrdln":"SF 9","note":null},"2205":{"sp":0,"desc":"(13:00) (Shotgun) M.Barkley pass deep left to C.Meredith pushed ob at SF 38 for 22 yards (J.Tartt).","qtr":3,"down":3,"players":{"00-0030533":[{"statId":15,"yards":22,"clubcode":"CHI","sequence":3,"playerName":"M.Barkley"},{"statId":111,"yards":18,"clubcode":"CHI","sequence":4,"playerName":"M.Barkley"}],"00-0032057":[{"statId":79,"yards":0,"clubcode":"SF","sequence":8,"playerName":"J.Tartt"}],"0":[{"statId":4,"yards":0,"clubcode":"CHI","sequence":1,"playerName":""},{"statId":6,"yards":0,"clubcode":"CHI","sequence":2,"playerName":""}],"00-0031912":[{"statId":21,"yards":22,"clubcode":"CHI","sequence":5,"playerName":"C.Meredith"},{"statId":115,"yards":0,"clubcode":"CHI","sequence":6,"playerName":"C.Meredith"},{"statId":113,"yards":4,"clubcode":"CHI","sequence":7,"playerName":"C.Meredith"}]},"ydsnet":37,"posteam":"CHI","time":"13:00","ydstogo":6,"yrdln":"CHI 40","note":null},"2297":{"sp":0,"desc":"(10:50) J.Langford left tackle to SF 9 for 2 yards (G.Hodges).","qtr":3,"down":1,"players":{"00-0031569":[{"statId":10,"yards":2,"clubcode":"CHI","sequence":1,"playerName":"J.Langford"}],"00-0030385":[{"statId":79,"yards":0,"clubcode":"SF","sequence":2,"playerName":"G.Hodges"}]},"ydsnet":66,"posteam":"CHI","time":"10:50","ydstogo":10,"yrdln":"SF 11","note":null},"2252":{"sp":0,"desc":"(12:15) J.Howard left guard to SF 35 for 3 yards (N.Bellore).","qtr":3,"down":2,"players":{"00-0028292":[{"statId":79,"yards":0,"clubcode":"SF","sequence":2,"playerName":"N.Bellore"}],"00-0032780":[{"statId":10,"yards":3,"clubcode":"CHI","sequence":1,"playerName":"J.Howard"}]},"ydsnet":40,"posteam":"CHI","time":"12:15","ydstogo":10,"yrdln":"SF 38","note":null},"2129":{"sp":0,"desc":"(14:24) M.Barkley pass incomplete deep left to J.Bellamy. PENALTY on SF-T.Brock, Defensive Holding, 5 yards, enforced at CHI 31 - No Play.","qtr":3,"down":2,"players":{"0":[{"statId":5,"yards":0,"clubcode":"CHI","sequence":1,"playerName":""}],"00-0027375":[{"statId":93,"yards":5,"clubcode":"SF","sequence":2,"playerName":"T.Brock"}]},"ydsnet":11,"posteam":"CHI","time":"14:24","ydstogo":4,"yrdln":"CHI 31","note":"PENALTY"},"2107":{"sp":0,"desc":"(15:00) J.Howard left tackle to CHI 31 for 6 yards (N.Bellore).","qtr":3,"down":1,"players":{"00-0028292":[{"statId":79,"yards":0,"clubcode":"SF","sequence":2,"playerName":"N.Bellore"}],"00-0032780":[{"statId":10,"yards":6,"clubcode":"CHI","sequence":1,"playerName":"J.Howard"}]},"ydsnet":6,"posteam":"CHI","time":"15:00","ydstogo":10,"yrdln":"CHI 25","note":null},"2273":{"sp":0,"desc":"(11:32) (Shotgun) M.Barkley pass deep left to J.Bellamy to SF 11 for 24 yards (R.Robinson).","qtr":3,"down":3,"players":{"00-0030533":[{"statId":15,"yards":24,"clubcode":"CHI","sequence":3,"playerName":"M.Barkley"},{"statId":111,"yards":24,"clubcode":"CHI","sequence":4,"playerName":"M.Barkley"}],"0":[{"statId":4,"yards":0,"clubcode":"CHI","sequence":1,"playerName":""},{"statId":6,"yards":0,"clubcode":"CHI","sequence":2,"playerName":""}],"00-0029319":[{"statId":21,"yards":24,"clubcode":"CHI","sequence":5,"playerName":"J.Bellamy"},{"statId":115,"yards":0,"clubcode":"CHI","sequence":6,"playerName":"J.Bellamy"},{"statId":113,"yards":0,"clubcode":"CHI","sequence":7,"playerName":"J.Bellamy"}],"00-0032410":[{"statId":79,"yards":0,"clubcode":"SF","sequence":8,"playerName":"R.Robinson"}]},"ydsnet":64,"posteam":"CHI","time":"11:32","ydstogo":7,"yrdln":"SF 35","note":null},"2365":{"sp":1,"desc":"C.Barth extra point is GOOD, Center-P.Scales, Holder-P.O'Donnell.","qtr":3,"down":0,"players":{"00-0026138":[{"statId":72,"yards":0,"clubcode":"CHI","sequence":1,"playerName":"C.Barth"}]},"ydsnet":75,"posteam":"CHI","time":"09:32","ydstogo":0,"yrdln":"SF 15","note":"XP"}},"redzone":true,"end":{"qtr":3,"time":"09:32","yrdln":"SF 2","team":"CHI"},"start":{"qtr":3,"time":"15:00","yrdln":"CHI 25","team":"CHI"},"result":"Touchdown","penyds":5,"postime":"5:28","posteam":"CHI","numplays":13,"ydsgained":70},"20":{"qtr":4,"fds":1,"plays":{"3431":{"sp":0,"desc":"(11:16) J.Howard right tackle to CHI 41 for 2 yards (Q.Dial).","qtr":4,"down":2,"players":{"00-0032780":[{"statId":10,"yards":2,"clubcode":"CHI","sequence":2,"playerName":"J.Howard"}],"0":[{"statId":3,"yards":0,"clubcode":"CHI","sequence":1,"playerName":""}],"00-0030088":[{"statId":79,"yards":0,"clubcode":"SF","sequence":3,"playerName":"Q.Dial"}]},"ydsnet":10,"posteam":"CHI","time":"11:16","ydstogo":2,"yrdln":"CHI 39","note":null},"3522":{"sp":0,"desc":"(8:14) (Punt formation) P.O'Donnell punts 52 yards to end zone, Center-P.Scales, Touchback. PENALTY on SF-R.Robinson, Offensive Holding, 10 yards, enforced at SF 20.","qtr":4,"down":4,"players":{"00-0032410":[{"statId":93,"yards":10,"clubcode":"SF","sequence":3,"playerName":"R.Robinson"}],"0":[{"statId":40,"yards":0,"clubcode":"SF","sequence":2,"playerName":""}],"00-0031079":[{"statId":32,"yards":52,"clubcode":"CHI","sequence":1,"playerName":"P.O'Donnell"}]},"ydsnet":17,"posteam":"CHI","time":"08:14","ydstogo":3,"yrdln":"CHI 48","note":"PUNT"},"3456":{"sp":0,"desc":"(10:29) J.Howard right tackle to CHI 45 for 4 yards (A.Brooks). SF-Q.Dial was injured during the play.","qtr":4,"down":1,"players":{"00-0032780":[{"statId":10,"yards":4,"clubcode":"CHI","sequence":1,"playerName":"J.Howard"}],"00-0024495":[{"statId":79,"yards":0,"clubcode":"SF","sequence":2,"playerName":"A.Brooks"}]},"ydsnet":14,"posteam":"CHI","time":"10:29","ydstogo":10,"yrdln":"CHI 41","note":null},"3405":{"sp":0,"desc":"(11:54) J.Howard right end pushed ob at CHI 39 for 8 yards (A.Bethea). SF-N.Bellore was injured during the play.","qtr":4,"down":1,"players":{"00-0032780":[{"statId":10,"yards":8,"clubcode":"CHI","sequence":1,"playerName":"J.Howard"}],"00-0024421":[{"statId":79,"yards":0,"clubcode":"SF","sequence":2,"playerName":"A.Bethea"}]},"ydsnet":8,"posteam":"CHI","time":"11:54","ydstogo":10,"yrdln":"CHI 31","note":null},"3501":{"sp":0,"desc":"(9:01) J.Howard left guard to CHI 48 for -1 yards (N.Bellore; C.Jones).","qtr":4,"down":3,"players":{"00-0028292":[{"statId":82,"yards":0,"clubcode":"SF","sequence":4,"playerName":"N.Bellore"}],"00-0032780":[{"statId":10,"yards":-1,"clubcode":"CHI","sequence":2,"playerName":"J.Howard"}],"0":[{"statId":7,"yards":0,"clubcode":"CHI","sequence":1,"playerName":""},{"statId":95,"yards":-1,"clubcode":"CHI","sequence":3,"playerName":""}],"00-0030106":[{"statId":82,"yards":0,"clubcode":"SF","sequence":5,"playerName":"C.Jones"}]},"ydsnet":17,"posteam":"CHI","time":"09:01","ydstogo":2,"yrdln":"CHI 49","note":null},"3480":{"sp":0,"desc":"(9:45) J.Howard right tackle to CHI 49 for 4 yards (G.Dorsey).","qtr":4,"down":2,"players":{"00-0032780":[{"statId":10,"yards":4,"clubcode":"CHI","sequence":1,"playerName":"J.Howard"}],"00-0026145":[{"statId":79,"yards":0,"clubcode":"SF","sequence":2,"playerName":"G.Dorsey"}]},"ydsnet":18,"posteam":"CHI","time":"09:45","ydstogo":6,"yrdln":"CHI 45","note":null}},"redzone":true,"end":{"qtr":4,"time":"08:05","yrdln":"CHI 48","team":"CHI"},"start":{"qtr":4,"time":"11:54","yrdln":"CHI 31","team":"CHI"},"result":"Punt","penyds":0,"postime":"3:49","posteam":"CHI","numplays":6,"ydsgained":17},"3":{"qtr":1,"fds":0,"plays":{"468":{"sp":0,"desc":"(8:00) (No Huddle, Shotgun) C.Kaepernick sacked at SF 21 for -5 yards (E.Goldman).","qtr":1,"down":3,"players":{"0":[{"statId":7,"yards":0,"clubcode":"SF","sequence":1,"playerName":""}],"00-0027974":[{"statId":20,"yards":-5,"clubcode":"SF","sequence":2,"playerName":"C.Kaepernick"}],"00-0031551":[{"statId":83,"yards":-5,"clubcode":"CHI","sequence":3,"playerName":"E.Goldman"},{"statId":110,"yards":0,"clubcode":"CHI","sequence":4,"playerName":"E.Goldman"},{"statId":79,"yards":0,"clubcode":"CHI","sequence":5,"playerName":"E.Goldman"},{"statId":120,"yards":0,"clubcode":"CHI","sequence":6,"playerName":"E.Goldman"},{"statId":402,"yards":5,"clubcode":"CHI","sequence":7,"playerName":"E.Goldman"}]},"ydsnet":1,"posteam":"SF","time":"08:00","ydstogo":4,"yrdln":"SF 26","note":null},"447":{"sp":0,"desc":"(8:39) (No Huddle, Shotgun) C.Kaepernick scrambles left end pushed ob at SF 26 for 2 yards (D.Bush).","qtr":1,"down":2,"players":{"00-0032774":[{"statId":79,"yards":0,"clubcode":"CHI","sequence":2,"playerName":"D.Bush"}],"00-0027974":[{"statId":10,"yards":2,"clubcode":"SF","sequence":1,"playerName":"C.Kaepernick"}]},"ydsnet":6,"posteam":"SF","time":"08:39","ydstogo":6,"yrdln":"SF 24","note":null},"426":{"sp":0,"desc":"(9:10) (Shotgun) C.Hyde left tackle to SF 24 for 4 yards (N.Kwiatkoski).","qtr":1,"down":1,"players":{"00-0032773":[{"statId":79,"yards":0,"clubcode":"CHI","sequence":2,"playerName":"N.Kwiatkoski"}],"00-0031045":[{"statId":10,"yards":4,"clubcode":"SF","sequence":1,"playerName":"C.Hyde"}]},"ydsnet":4,"posteam":"SF","time":"09:10","ydstogo":10,"yrdln":"SF 20","note":null},"487":{"sp":0,"desc":"(7:32) (Punt formation) B.Pinion punts 37 yards to CHI 42, Center-K.Nelson, downed by SF.","qtr":1,"down":4,"players":{"00-0032065":[{"statId":29,"yards":37,"clubcode":"SF","sequence":1,"playerName":"B.Pinion"}],"0":[{"statId":38,"yards":0,"clubcode":"CHI","sequence":2,"playerName":""}]},"ydsnet":1,"posteam":"SF","time":"07:32","ydstogo":9,"yrdln":"SF 21","note":"PUNT"}},"redzone":true,"end":{"qtr":1,"time":"07:22","yrdln":"SF 21","team":"SF"},"start":{"qtr":1,"time":"09:10","yrdln":"SF 20","team":"SF"},"result":"Punt","penyds":0,"postime":"1:48","posteam":"SF","numplays":4,"ydsgained":1},"2":{"qtr":1,"fds":1,"plays":{"297":{"sp":0,"desc":"(11:15) J.Howard right tackle to SF 46 for 17 yards (A.Bethea; J.Tartt).","qtr":1,"down":2,"players":{"00-0032780":[{"statId":10,"yards":17,"clubcode":"CHI","sequence":2,"playerName":"J.Howard"}],"00-0032057":[{"statId":82,"yards":0,"clubcode":"SF","sequence":4,"playerName":"J.Tartt"}],"0":[{"statId":3,"yards":0,"clubcode":"CHI","sequence":1,"playerName":""}],"00-0024421":[{"statId":82,"yards":0,"clubcode":"SF","sequence":3,"playerName":"A.Bethea"}]},"ydsnet":20,"posteam":"CHI","time":"11:15","ydstogo":7,"yrdln":"CHI 37","note":null},"391":{"sp":0,"desc":"(9:19) (Punt formation) P.O'Donnell punts 44 yards to end zone, Center-P.Scales, Touchback.","qtr":1,"down":4,"players":{"0":[{"statId":40,"yards":0,"clubcode":"SF","sequence":2,"playerName":""}],"00-0031079":[{"statId":32,"yards":44,"clubcode":"CHI","sequence":1,"playerName":"P.O'Donnell"}]},"ydsnet":22,"posteam":"CHI","time":"09:19","ydstogo":8,"yrdln":"SF 44","note":"PUNT"},"275":{"sp":0,"desc":"(11:51) J.Howard left end to CHI 37 for 3 yards (N.Bellore).","qtr":1,"down":1,"players":{"00-0028292":[{"statId":79,"yards":0,"clubcode":"SF","sequence":2,"playerName":"N.Bellore"}],"00-0032780":[{"statId":10,"yards":3,"clubcode":"CHI","sequence":1,"playerName":"J.Howard"}]},"ydsnet":3,"posteam":"CHI","time":"11:51","ydstogo":10,"yrdln":"CHI 34","note":null},"343":{"sp":0,"desc":"(9:59) (Shotgun) M.Barkley pass incomplete short left to K.Carey (R.Robinson).","qtr":1,"down":2,"players":{"00-0030533":[{"statId":14,"yards":0,"clubcode":"CHI","sequence":1,"playerName":"M.Barkley"},{"statId":112,"yards":0,"clubcode":"CHI","sequence":4,"playerName":"M.Barkley"}],"00-0031057":[{"statId":115,"yards":0,"clubcode":"CHI","sequence":2,"playerName":"K.Carey"}],"00-0032410":[{"statId":85,"yards":0,"clubcode":"SF","sequence":3,"playerName":"R.Robinson"}]},"ydsnet":17,"posteam":"CHI","time":"09:59","ydstogo":13,"yrdln":"SF 49","note":null},"318":{"sp":0,"desc":"(10:37) M.Barkley FUMBLES (Aborted) at SF 46, recovered by CHI-J.Howard at SF 49. J.Howard to SF 49 for no gain (G.Hodges).","qtr":1,"down":1,"players":{"00-0030533":[{"statId":10,"yards":0,"clubcode":"CHI","sequence":1,"playerName":"M.Barkley"},{"statId":57,"yards":-3,"clubcode":"CHI","sequence":2,"playerName":"M.Barkley"},{"statId":53,"yards":0,"clubcode":"CHI","sequence":3,"playerName":"M.Barkley"}],"00-0032780":[{"statId":55,"yards":0,"clubcode":"CHI","sequence":4,"playerName":"J.Howard"}],"00-0030385":[{"statId":79,"yards":0,"clubcode":"SF","sequence":5,"playerName":"G.Hodges"},{"statId":120,"yards":0,"clubcode":"SF","sequence":6,"playerName":"G.Hodges"},{"statId":402,"yards":3,"clubcode":"SF","sequence":7,"playerName":"G.Hodges"}]},"ydsnet":17,"posteam":"CHI","time":"10:37","ydstogo":10,"yrdln":"SF 46","note":"FUMBLE"},"365":{"sp":0,"desc":"(9:53) (Shotgun) M.Barkley scrambles left end pushed ob at SF 44 for 5 yards (M.Wilhoite).","qtr":1,"down":3,"players":{"00-0030533":[{"statId":10,"yards":5,"clubcode":"CHI","sequence":2,"playerName":"M.Barkley"}],"00-0028836":[{"statId":79,"yards":0,"clubcode":"SF","sequence":3,"playerName":"M.Wilhoite"}],"0":[{"statId":7,"yards":0,"clubcode":"CHI","sequence":1,"playerName":""}]},"ydsnet":22,"posteam":"CHI","time":"09:53","ydstogo":13,"yrdln":"SF 49","note":null}},"redzone":true,"end":{"qtr":1,"time":"09:10","yrdln":"SF 44","team":"CHI"},"start":{"qtr":1,"time":"11:51","yrdln":"CHI 34","team":"CHI"},"result":"Punt","penyds":0,"postime":"2:41","posteam":"CHI","numplays":6,"ydsgained":22}},"home":{"abbr":"CHI","score":{"4":5,"T":26,"1":0,"3":14,"2":7,"5":0},"stats":{"passing":{"00-0030533":{"yds":192,"ints":0,"att":18,"twoptm":0,"cmp":11,"name":"M.Barkley","twopta":0,"tds":0}},"fumbles":{"00-0030533":{"yds":-3,"lost":0,"trcv":0,"rcv":0,"tot":1,"name":"M.Barkley"},"00-0032780":{"yds":0,"lost":0,"trcv":1,"rcv":1,"tot":0,"name":"J.Howard"},"00-0029388":{"yds":0,"lost":1,"trcv":0,"rcv":0,"tot":1,"name":"D.Thompson"}},"puntret":{"00-0031904":{"lngtd":0,"lng":3,"ret":1,"avg":3,"name":"B.Callahan","tds":0}},"team":{"penyds":40,"pyds":184,"pen":5,"pt":6,"ryds":142,"totfd":19,"trnovr":1,"ptavg":28,"ptyds":233,"top":"31:18","totyds":326},"kicking":{"00-0026138":{"xpmade":3,"xpa":3,"xpb":0,"fga":1,"fgm":1,"xpmissed":0,"name":"C.Barth","xptot":3,"fgyds":45,"totpfg":3}},"receiving":{"00-0032098":{"yds":13,"lngtd":0,"lng":7,"twoptm":0,"twopta":0,"name":"D.Brown","rec":2,"tds":0},"00-0029319":{"yds":93,"lngtd":0,"lng":31,"twoptm":0,"twopta":0,"name":"J.Bellamy","rec":4,"tds":0},"00-0029388":{"yds":19,"lngtd":0,"lng":11,"twoptm":0,"twopta":0,"name":"D.Thompson","rec":2,"tds":0},"00-0031912":{"yds":67,"lngtd":0,"lng":28,"twoptm":0,"twopta":0,"name":"C.Meredith","rec":3,"tds":0}},"defense":{"00-0026180":{"tkl":2,"int":0,"name":"T.Porter","sk":0,"ffum":0,"ast":0},"00-0032581":{"tkl":3,"int":0,"name":"C.LeBlanc","sk":0,"ffum":0,"ast":0},"00-0029657":{"tkl":8,"int":0,"name":"A.Hicks","sk":2,"ffum":1,"ast":2},"00-0030048":{"tkl":2,"int":0,"name":"C.Washington","sk":0,"ffum":0,"ast":0},"00-0031915":{"tkl":2,"int":0,"name":"J.Timu","sk":0,"ffum":0,"ast":1},"00-0033072":{"tkl":4,"int":0,"name":"L.Floyd","sk":2,"ffum":0,"ast":0},"00-0031989":{"tkl":7,"int":0,"name":"H.Jones-Quartey","sk":0,"ffum":0,"ast":2},"00-0027573":{"tkl":0,"int":0,"name":"M.Unrein","sk":0,"ffum":0,"ast":1},"00-0031551":{"tkl":2,"int":0,"name":"E.Goldman","sk":1,"ffum":0,"ast":0},"00-0032774":{"tkl":2,"int":0,"name":"D.Bush","sk":0,"ffum":0,"ast":0},"00-0027808":{"tkl":1,"int":0,"name":"W.Young","sk":1,"ffum":0,"ast":0},"00-0032773":{"tkl":9,"int":0,"name":"N.Kwiatkoski","sk":0,"ffum":0,"ast":0}},"kickret":{"00-0031706":{"lngtd":0,"lng":5,"ret":1,"avg":5,"name":"P.Lasike","tds":0},"00-0031904":{"lngtd":0,"lng":0,"ret":1,"avg":0,"name":"B.Callahan","tds":0},"00-0029388":{"lngtd":0,"lng":28,"ret":1,"avg":28,"name":"D.Thompson","tds":0}},"rushing":{"00-0030533":{"yds":3,"att":4,"lngtd":0,"lng":5,"twoptm":0,"twopta":0,"name":"M.Barkley","tds":0},"00-0032780":{"yds":117,"att":32,"lngtd":5,"lng":25,"twoptm":0,"twopta":0,"name":"J.Howard","tds":3},"00-0031057":{"yds":8,"att":2,"lngtd":0,"lng":4,"twoptm":0,"twopta":0,"name":"K.Carey","tds":0},"00-0029319":{"yds":12,"att":1,"lngtd":0,"lng":12,"twoptm":0,"twopta":0,"name":"J.Bellamy","tds":0},"00-0031569":{"yds":2,"att":1,"lngtd":0,"lng":2,"twoptm":0,"twopta":0,"name":"J.Langford","tds":0}},"punting":{"00-0031079":{"yds":233,"lng":52,"pts":6,"avg":28,"name":"P.O'Donnell","i20":2}}},"players":null,"to":2},"media":null,"note":null,"posteam":"CHI","qtr":"Final","redzone":true,"scrsummary":{"3208":{"desc":"C.Barth 45 yd. Field Goal Drive: 7 plays, 37 yards in 3:19","players":{"C.Barth":"00-0026138"},"qtr":4,"type":"FG","team":"CHI"},"3972":{"desc":"B.Gabbert sacked in end zone by L.Floyd for a Safety","players":{"L.Floyd":"00-0033072","B.Gabbert":"00-0027948"},"qtr":4,"type":"SAF","team":"CHI"},"2342":{"desc":"J.Howard 2 yd. run (C.Barth kick is good) Drive: 10 plays, 75 yards in 5:28","players":{"":"0","J.Howard":"00-0032780","C.Barth":"00-0026138"},"qtr":3,"type":"TD","team":"CHI"},"2622":{"desc":"J.Howard 5 yd. run (C.Barth kick is good) Drive: 4 plays, 59 yards in 2:13","players":{"":"0","J.Howard":"00-0032780","C.Barth":"00-0026138"},"qtr":3,"type":"TD","team":"CHI"},"1999":{"desc":"J.Howard 1 yd. run (C.Barth kick is good) Drive: 8 plays, 81 yards in 1:25","players":{"":"0","J.Howard":"00-0032780","C.Barth":"00-0026138"},"qtr":2,"type":"TD","team":"CHI"},"1372":{"desc":"P.Dawson 31 yd. Field Goal Drive: 4 plays, 6 yards in 2:12","players":{"P.Dawson":"00-0004091"},"qtr":2,"type":"FG","team":"SF"},"1691":{"desc":"P.Dawson 28 yd. Field Goal Drive: 9 plays, 27 yards in 4:51","players":{"P.Dawson":"00-0004091"},"qtr":2,"type":"FG","team":"SF"}},"stadium":null,"togo":0,"weather":null,"yl":""},"nextupdate":{"away":293,"clock":293,"down":293,"drives":293,"home":293,"media":293,"note":293,"posteam":293,"qtr":293,"redzone":293,"scrsummary":293,"stadium":293,"togo":293,"weather":293,"yl":293}}